[{"tweets_quantity": 326},{"created_at": "2023-02-09T00:29:04.000Z", "text": "o michael dando um ipod no amigo oculto do escrit\u00f3rio e ganhando uma luva de forno, estou fascinada com essa s\u00e9rie", "id": "1623479056531324929"},{"created_at": "2023-02-08T23:58:24.000Z", "text": "@gabrieldemarque Dividir fone pra ouvir M5, bolo de churros, bolo de cenoura, amigo oculto de chocolate na p\u00e1scoa, chopadas, ficar admirando o povo de ed f\u00edsica, nossos rol\u00eas juntos, ai amigo pqp que SAUDADE!", "id": "1623471340635275264"},{"created_at": "2023-02-08T17:51:26.000Z", "text": "Amigo Oculto da minha fam\u00edlia! https://t.co/4xykwGSdX8", "id": "1623378989845717004"},{"created_at": "2023-02-08T16:39:43.000Z", "text": "Oposi\u00e7\u00e3o Mequetrefe, tem a maioria, ma$$$ pr\u00e1tica amigo oculto. https://t.co/vXN2XgClXr", "id": "1623360942628081684"},{"created_at": "2023-02-08T15:37:46.000Z", "text": "@pitonildes Eu j\u00e1 recebi um livro gospel de presente de amigo oculto no trabalho uma vez", "id": "1623345351653486595"},{"created_at": "2023-02-08T13:29:30.000Z", "text": "@Herpeto_cosas puedes ubicar a nuestro peque\u00f1o amigo oculto en la foto?  \n(Nivel: F\u00e1cil) https://t.co/PWhDR4sDrE", "id": "1623313072461938692"},{"created_at": "2023-02-08T03:35:40.000Z", "text": "@dennesousa1 Corrup\u00e7\u00e3o b\u00e1sica m\u00f3dulo um: como negar sempre, o papel do amigo oculto, eu n\u00e3o sei de nada, a utilidade de um parente falecido.", "id": "1623163626709295104"},{"created_at": "2023-02-08T00:21:33.000Z", "text": "A Mariana saindo do amigo oculto https://t.co/inD4cAr6bW", "id": "1623114775436599297"},{"created_at": "2023-02-07T23:47:27.000Z", "text": "o amigo oculto (filme)\nSHOW de atua\u00e7\u00e3o do robert de niro e da dakota fanning com apenas 10 anos. muito foda e final surpreendente tbm (9/10)", "id": "1623106194129690627"},{"created_at": "2023-02-07T22:10:48.000Z", "text": "@ttoqs \u00e9 pra Oli, migooo! o do amigo oculto j\u00e1 comprei hihi", "id": "1623081873541832705"},{"created_at": "2023-02-07T19:05:36.000Z", "text": "@fotocomrevolver Eu ia te dar um desse laranja no amigo oculto", "id": "1623035266494603265"},{"created_at": "2023-02-07T17:10:21.000Z", "text": "@igormirandasite Ganhei de amigo oculto o vinil.", "id": "1623006263457067015"},{"created_at": "2023-02-07T14:10:47.000Z", "text": "@gabiiCabreraa Era de esperarse que hagan esas cosas porque lo \u00faltimo que pas\u00f3 fue lo de nam , hasta el amigo oculto los comentarios porque ya se pasaron las inmaduras disque llamarse \" Army\" ellos no son propiedad de nadie , tienen vidas personales y se merecen respeto sea cu\u00e1l sea lo que hagn", "id": "1622961074214473730"},{"created_at": "2023-02-07T13:26:54.000Z", "text": "V\u00eddeo novo: Dei uma MELANCIA de presente no amigo oculto... https://t.co/ZLhSIqqSk0", "id": "1622950029437865991"},{"created_at": "2023-02-07T09:30:52.000Z", "text": "bestie resolveu tomar vergonha na cara, e dar meu presente do amigo oculto do ano passado, amei muito. https://t.co/kZZ0RPaspL", "id": "1622890629771436032"},{"created_at": "2023-02-07T04:55:32.000Z", "text": "\"quero um novo ano sem amigo oculto, \u00e9 pedir muito?\"", "id": "1622821338673971200"},{"created_at": "2023-02-07T02:12:04.000Z", "text": "uma vez fui suspenso por doar a folha do meu caderno para um miser\u00e1vel desenhar e ele fez simplesmente um xiriz\u00e3o na folha menssss!\neu fiquei at\u00e9 sem acreditar e ainda por cima perdi o amigo oculto! https://t.co/uEF2unWDdT", "id": "1622780201150152707"},{"created_at": "2023-02-07T02:05:32.000Z", "text": "Bora Mosca, n\u00e3o \u00e9 amigo oculto n\u00e3o (\"Essa pessoa.... \u00c9 uma pessoa muuuuito...\") #BBB23", "id": "1622778556848668672"},{"created_at": "2023-02-07T00:58:56.000Z", "text": "@cactossauro eu quase te mandei no amigo oculto", "id": "1622761795088785411"},{"created_at": "2023-02-07T00:52:48.000Z", "text": "hj que eu t\u00f4 usando a langerie/top que eu ganhei no amigo oculto da empresa e que pe\u00e7a confort\u00e1vel, eu amei", "id": "1622760253841342466"},{"created_at": "2023-02-07T00:28:16.000Z", "text": "Comprar presente pra amigo oculto \u00e9 t\u00e3o dif\u00edcil", "id": "1622754079817474050"},{"created_at": "2023-02-07T00:14:57.000Z", "text": "@zabelly_gp Pr\u00f3ximo amigo oculto vai ser de queijo", "id": "1622750727302000641"},{"created_at": "2023-02-06T20:31:35.000Z", "text": "@fvsgoth a\u00ed a gente s\u00f3 vai descartando os poss\u00edveis assassinos at\u00e9 descobrir quem \u00e9 o assassino, tipo em amigo oculto", "id": "1622694516695384066"},{"created_at": "2023-02-06T17:41:51.000Z", "text": "o \u00faltimo parece eu abrindo o presente de um certo amigo oculto https://t.co/Rt9ytGeXON", "id": "1622651799214628865"},{"created_at": "2023-02-06T16:19:53.000Z", "text": "bora fazer o amigo oculto agora uai hahaha", "id": "1622631175469555714"},{"created_at": "2023-02-06T15:29:47.000Z", "text": "T\u00e1 eu aqui lembrando do nosso amigo oculto de ontem , nossa t\u00f4 rindo por de mais kkkkkkk", "id": "1622618566842372101"},{"created_at": "2023-02-06T15:13:27.000Z", "text": "@tupanapoi HAHAHAHAAHA presente de amigo oculto a partir de 50 reais, esse a\u00ed entra", "id": "1622614456365682697"},{"created_at": "2023-02-06T12:51:24.000Z", "text": "@yoontaerin pro amigo oculto desse ano a gente pode criar algumas categorias ne", "id": "1622578706353999872"},{"created_at": "2023-02-06T02:47:18.000Z", "text": "Acabei de assistir o amigo oculto, filminho interessante, curti dms https://t.co/QtTsSjj8J5", "id": "1622426682362576897"},{"created_at": "2023-02-06T01:12:34.000Z", "text": "@Zachzinn_ @samuelvenancio @srgucec_ N\u00e3o \u00e9 um tiro no p\u00e9? Por exemplo: no fim d ano fui comprar presentes de amigo oculto de \u00faltima hora e n\u00e3o encontrei lojas oficiais pr\u00f3ximas de mim\u2026acho q deviam repensar nessa situa\u00e7\u00e3o sim, as frangas est\u00e3o espalhando lojas pra todo lado", "id": "1622402838658777089"},{"created_at": "2023-02-05T22:31:59.000Z", "text": "fui pro shopping com um presentinho pro amigo oculto, voltei com presentinhos pra mim e pro baby das meninas \ud83e\udd72\ud83e\udd79", "id": "1622362425809838080"},{"created_at": "2023-02-05T20:36:52.000Z", "text": "Vamos l\u00e1 fazer amigo oculto para dia 14\ud83d\ude2d", "id": "1622333457807417350"},{"created_at": "2023-02-05T20:23:17.000Z", "text": "Meu presente do amigo oculto do grupo de doramas finalmente chegou. \u00c9 um all star lindo e acho que vou usar ele no show essa semana.", "id": "1622330038795534336"},{"created_at": "2023-02-05T20:17:38.000Z", "text": "Eu estraguei o amigo oculto\u2026", "id": "1622328615982583814"},{"created_at": "2023-02-05T18:37:51.000Z", "text": "Meu grande amigo oculto @criabai me conhece \ud83e\udd7a https://t.co/2BkW9EY2fJ", "id": "1622303507070992385"},{"created_at": "2023-02-05T18:09:09.000Z", "text": "ai os cara me lan\u00e7a um amigo oculto em pleno fevereiro \ud83e\udd23\ud83e\udd23", "id": "1622296282495606791"},{"created_at": "2023-02-05T16:54:14.000Z", "text": "@apenasrata @anav_aguiarr quero uma toalha dessa  no nosso pr\u00f3ximo amigo oculto", "id": "1622277428281212929"},{"created_at": "2023-02-05T16:00:05.000Z", "text": "@anonymous_otacu Coffe cad\u00ea voc\u00ea pra mandar o email pro amigo oculto coffiiiweeeeeee", "id": "1622263803307073536"},{"created_at": "2023-02-05T14:58:53.000Z", "text": "@penelopwgarcia comic twt foi um surto kkk eu descobri ano passado que eu tava com a leti em um squad de sambucky e que ela que tinha me tirado num amigo oculto que teve l\u00e1", "id": "1622248402049241091"},{"created_at": "2023-02-05T13:50:44.000Z", "text": "@henritxt @paramore amigooo eu ganhei de amigo oculto, mas acho que foi aqui: \nhttps://t.co/SQxjtWwCoC", "id": "1622231251368255491"},{"created_at": "2023-02-05T13:27:20.000Z", "text": "https://t.co/7zywKE7mYZ\n\nNossa, esse do amigo oculto tem plot twist doido", "id": "1622225364205408258"},{"created_at": "2023-02-05T11:59:32.000Z", "text": "o amigo oculto da akatsuki ainda me faz rir", "id": "1622203266128822272"},{"created_at": "2023-02-05T04:16:00.000Z", "text": "Todo amigo oculto daqui de casa eu tiro meu pai kkkkkkk", "id": "1622086615316267010"},{"created_at": "2023-02-05T02:49:50.000Z", "text": "@Carolarte_forro Sem d\u00favida os melhores. Ganhei esse CD num amigo oculto da escola. Os jovens de hj nem sabem o q CD. Kkkkk\nCARLA NO ALTAS HORAS", "id": "1622064928940072960"},{"created_at": "2023-02-05T02:10:18.000Z", "text": "GENTE minha amg me tirou no amigo oculto e junto com o presente me deu 4  b1s xtr4s mds eu tenho tanta fama de quem n para de comer", "id": "1622054980931788802"},{"created_at": "2023-02-05T01:29:19.000Z", "text": "@forpansexual Minha fam\u00edlia sabe, ganhei at\u00e9 uma bandeira arco \u00edris de amigo oculto da minha irm\u00e3 no natal do ano retrasado akskskdkkdkddkksks", "id": "1622044666139926529"},{"created_at": "2023-02-05T00:56:11.000Z", "text": "@ATROMBETA3 Existe amigo oculto, palavra oculta e existe a beleza oculta.", "id": "1622036328706629633"},{"created_at": "2023-02-05T00:05:55.000Z", "text": "Quero um amigo oculto assim https://t.co/Sypoe4K4Lr", "id": "1622023679365320705"},{"created_at": "2023-02-04T23:54:48.000Z", "text": "@demianvante \" A dor \u00e9 inevit\u00e1vel o sofrimento \u00e9 opcional\" - Pain, Amigo oculto da akatsuki.", "id": "1622020880707604481"},{"created_at": "2023-02-04T17:47:58.000Z", "text": "\ud83d\udc39: Quem vai saber se voc\u00ea n\u00e3o contar\n\n*Manitto: \u00e9 um jogo em que uma pessoa do grupo \u00e9 designada como seu amigo secreto, a\u00ed ele te ajuda com um presente secreto (algo como amigo oculto)", "id": "1621928566740107265"},{"created_at": "2023-02-04T16:58:35.000Z", "text": "@shitpostverdade amigo oculto deixa um clima de satanismo ne", "id": "1621916135493959680"},{"created_at": "2023-02-04T15:15:15.000Z", "text": "Preparando para mandar para o meu pr\u00f3ximo amigo oculto da cidade https://t.co/Z8vQf0uBg2", "id": "1621890133623463942"},{"created_at": "2023-02-04T14:13:24.000Z", "text": "@eliasvantine nesse amigo oculto dei Garoto e ganhei Samba (literalmente)", "id": "1621874567118471168"},{"created_at": "2023-02-04T12:29:36.000Z", "text": "@gus_vasconcllos @shitpostverdade vou te dar isso ai de amigo oculto se eu tirar teu nome\ud83d\ude44\ud83d\ude44\ud83d\ude44", "id": "1621848447165894662"},{"created_at": "2023-02-04T06:34:52.000Z", "text": "@shitpostverdade @moreiragrazy05 eu vou te dar isso aq de amigo oculto", "id": "1621759174731235329"},{"created_at": "2023-02-04T03:12:52.000Z", "text": "@shitpostverdade @souzinhai vou lhe presentear com isso quando ter amigo oculto ou no seu anv", "id": "1621708337552171008"},{"created_at": "2023-02-04T02:46:06.000Z", "text": "amigo oculto so me faz lembrar do dia que meu pai deu um caderno p um mlk da familia num natal kkkkkkkkkk https://t.co/vnox2XqRVJ", "id": "1621701601801936897"},{"created_at": "2023-02-04T02:30:25.000Z", "text": "lembrando aq q no natal de 2016 a gente fez um amigo oculto que chama 10 em 10 que consistia em: meus pais entregarem e tbm tinham s\u00f3 R$ 10,00 pra comprar o presente da pessoa que vc tirou e vc s\u00f3 tinha 10min pra achar = uma fam\u00edlia de 5 pessoas, correndo loucamente no Carrefour.", "id": "1621697656924913666"},{"created_at": "2023-02-04T01:30:24.000Z", "text": "@OBQDC @naosalvo j\u00e1 pediu de amigo oculto?", "id": "1621682552841900032"},{"created_at": "2023-02-04T00:10:49.000Z", "text": "@shitpostverdade @loiraagstsa ideia de amigo oculto", "id": "1621662525208018944"},{"created_at": "2023-02-03T23:27:37.000Z", "text": "@V_Moreto @shitpostverdade quero de amigo oculto", "id": "1621651650724208641"},{"created_at": "2023-02-03T21:23:35.000Z", "text": "O Anderson Torres ganhou a minuta do golpe no amigo oculto de natal.", "id": "1621620439628783619"},{"created_at": "2023-02-03T21:23:26.000Z", "text": "@pesquisas_2022 O Anderson Torres ganhou a minuta do golpe no amigo oculto de natal.", "id": "1621620401452290054"},{"created_at": "2023-02-03T20:08:27.000Z", "text": "@pcousaquiviti \u00c9 hj q tu vai usar os pratos q tu ganhou no amigo oculto ent\u00e3o?", "id": "1621601532423675905"},{"created_at": "2023-02-03T19:53:24.000Z", "text": "Amigo oculto. https://t.co/WEYAsh8D4D", "id": "1621597742744076288"},{"created_at": "2023-02-03T19:52:19.000Z", "text": "@GeneralGirao @Sandrarso1 T\u00e3o brincando de amigo oculto", "id": "1621597470437302274"},{"created_at": "2023-02-03T17:16:40.000Z", "text": "@kordflayer eu j\u00e1 sonhei q me deram um chocolate no amigo oculto, e eu comecei a chorar ((n\u00e3o gosto mt de chocolate, s\u00f3 de alguns espec\u00edficos))//", "id": "1621558300511723522"},{"created_at": "2023-02-03T16:22:29.000Z", "text": "Pedi Ozempic no amigo oculto da firma", "id": "1621544664141598720"},{"created_at": "2023-02-03T15:18:46.000Z", "text": "@AtaidesLuisa Amigo oculto do ano novo e afins", "id": "1621528630567346176"},{"created_at": "2023-02-03T14:22:29.000Z", "text": "Fizemos um amigo oculto que n\u00e3o aconteceu, e deixamos pra viagem do carnaval, t\u00f4 doida pra saber quem me tirou e receber meu presente kk", "id": "1621514463882125312"},{"created_at": "2023-02-03T06:35:36.000Z", "text": "@javizqui Llama inmediatamente al Marrano y fel\u00edcitale por su semblante: primero amigo oculto de Galli, despu\u00e9s, humillado y plantado en el altar por su enemigo; espiador espiado y, por si fuera poco, paseador de Biden.\nA este pobre encomiendas tu alma: BRAVO!!!!\nMayo se acerca..", "id": "1621396969787727872"},{"created_at": "2023-02-03T03:04:27.000Z", "text": "Ganhei um dos melhores presentes do amigo oculto da turma,  \u00e1lcool e chocolate \ud83d\udd90\ufe0f\ud83d\ude0b", "id": "1621343832380932096"},{"created_at": "2023-02-03T02:32:50.000Z", "text": "rip amigo oculto lutei tanto o cancelarem e me arrependi", "id": "1621335875006111745"},{"created_at": "2023-02-03T02:12:56.000Z", "text": "Era uma vez um amigo oculto\u2026", "id": "1621330869100101632"},{"created_at": "2023-02-03T01:45:44.000Z", "text": "Nossa eu vi um video do amigo oculto da empresa do ano passado e to mega mal, que saudade do pessoal que saiu \ud83d\ude22", "id": "1621324024226750466"},{"created_at": "2023-02-03T00:52:44.000Z", "text": "@JornalDaCidadeO Ser\u00e1 que foi avisado que \u00e9 um amigo oculto? n\u00e9?", "id": "1621310685467611136"},{"created_at": "2023-02-03T00:51:45.000Z", "text": "me preparando psicologicamente para o evento amigo oculto que vou ter amanh\u00e3, eu odeio muito amigo oculto (mesmo tendo tirado uma pessoa que gosto bastante)", "id": "1621310436841820160"},{"created_at": "2023-02-03T00:38:48.000Z", "text": "eu tenho um sonho: que cancelem esse amigo oculto", "id": "1621307176668078084"},{"created_at": "2023-02-02T23:28:08.000Z", "text": "A mo\u00e7a la da loja q tava de f\u00e9rias ke chega hoje\n\"Olha voc\u00ea comprou o allstar que vc queria? Ou ganhou no amigo oculto? N\u00e3o quem ganhou foi o ...\"\nEu comprei ele em dezembro, e ja paguei ele todo em +-1 m\u00eas, paguei a primeira parcela em 05/01 e a \u00faltima la pro dia 10 jjjjkkk", "id": "1621289396921040899"},{"created_at": "2023-02-02T22:51:59.000Z", "text": "@mdpopv Boa noite mam\u00e3e, amigo oculto, ilha do medo", "id": "1621280295478595584"},{"created_at": "2023-02-02T22:12:18.000Z", "text": "Grazi: FINALMENTE A GENTE CONSEGUIU TE ENGANARRRR!!! TO ME SENTINDO REALIZADA! \n\nFiquei uns 5 min me sentindo enganada!!! \n\nElas realmente sentiram por eu descobrir quem cada uma tirou no amigo oculto KKKKKK", "id": "1621270312301076480"},{"created_at": "2023-02-02T22:08:25.000Z", "text": "entrei na botic\u00e1rio pra comprar um creme de m\u00e3o pro amigo oculto da empresa e sai de l\u00e1 com um perfume de 200,00 pq fiquei com vergonha de falar n\u00e3o pra vendedora que me ofereceu https://t.co/1qnzMzp0aY", "id": "1621269335158263814"},{"created_at": "2023-02-02T21:36:15.000Z", "text": "@eliciacarvalho @leilagnc @paginalixo1 Vou te dar se eu sair de novo com vc no amigo oculto kkkkk", "id": "1621261240499671040"},{"created_at": "2023-02-02T21:25:00.000Z", "text": "amanh\u00e3 finalmente vai ter a confraterniza\u00e7\u00e3o de final de ano do meu trabalho, que acabou sendo adiada pois uma amiga perdeu a m\u00e3e, e agora tenho que me preparar pra um dos maiores terrores da minha vida: amigo oculto", "id": "1621258406056132608"},{"created_at": "2023-02-02T20:45:31.000Z", "text": "@igormirandasite She, sempre que escuto qualquer m\u00fasica desse \u00e1lbum parece que entro num t\u00fanel do tempo e volto a ter 14 anos, ganhei de presente no amigo oculto da escola", "id": "1621248470983098369"},{"created_at": "2023-02-02T19:28:35.000Z", "text": "eu amo d+ o xxt pprt, a gnt e t\u00e3o desorganizado junto que nem um amigo oculto a gnt consegue fazer", "id": "1621229108205174784"},{"created_at": "2023-02-02T17:56:12.000Z", "text": "@mrsmaryneves Saudades de quando eu trabalhava em Botafogo e tinha festa no \u00f4nibus. Era festa de anivers\u00e1rio, amigo oculto, carnaval, caf\u00e9 da manh\u00e3, tudo era motivo de festa. E toda sexta-feira na volta tinha cerveja, salgadinhos e pagode", "id": "1621205862269304834"},{"created_at": "2023-02-02T16:18:42.000Z", "text": "@danusarbc AFF Maria mulher. Me lembra o filme O Amigo Oculto. \nMas assim, eu tenho uma amiga que sei tudo dela, onde morava a hist\u00f3ria da fam\u00edlia e mainha n\u00e3o lembra dessa querida. N\u00e3o julgo Luna hahhshs Candy \u00e9 a J\u00e9ssica dela", "id": "1621181325674745861"},{"created_at": "2023-02-02T13:04:55.000Z", "text": "@Ytynfu Se eu pudesse levava pra voc\u00ea , quando eu vou no mercadinho aqui perto , sempre lembro do nosso amigo oculto, e eu fiquei doida tentando achar o ferreiro Rocher kkk", "id": "1621132558623965184"},{"created_at": "2023-02-02T11:46:08.000Z", "text": "@Cris_Destra Certo...\nN\u00e3o sem antes ph@der o povo brasileiro \u00e9 mostrar toda sua covardia.\nMeu marido gostava dele, eu nunca confiei.\nEu estava certa, como muitas vezes.\nKim, Joice, frota,os irm\u00e3os, Do Val, Kajuru, etc...\nVem mais por a\u00ed\nAguardemos\nMelhor um inimigo declarado q um amigo oculto", "id": "1621112731549200384"},{"created_at": "2023-02-02T11:43:07.000Z", "text": "@npaiva_gabriel @maracatrua Eu gosto um pouquinho mais de voc\u00ea pela ousadia de pedir uma jock num amigo oculto de empresa \u2764\ufe0f", "id": "1621111971142635520"},{"created_at": "2023-02-02T05:38:45.000Z", "text": "Eu ameeei meu presente de amigo oculto, vou poder usar mto nos bloquinhos.", "id": "1621020277256617986"},{"created_at": "2023-02-02T05:37:08.000Z", "text": "Gente eu n\u00e3o sei voc\u00eas, mas eu amo amigo oculto, amo a energia ca\u00f3tica que tem, amo ficar ensaiando o meu discurso  \ud83d\ude0d\ud83d\ude0d", "id": "1621019870161952769"},{"created_at": "2023-02-02T03:59:59.000Z", "text": "@alertatotal Prezado, bom dia, afinal h\u00e1 de ser novo. Uma coisa me incomodou muito ontem no Senado.Os que mais defendem a pacifica\u00e7\u00e3o e unifica\u00e7\u00e3o do pa\u00eds,brincavam,e ouviam gargalhadas, de que regi\u00e3o deveria ter vindo alguns votos,\u00e0 medida que eram divulgados. Parecia amigo oculto da firma.", "id": "1620995419252875265"},{"created_at": "2023-02-02T03:00:52.000Z", "text": "@larimanoela E eu ganhei esse blush no amigo oculto pa eu pedi ne . Eu AMO", "id": "1620980542911954946"},{"created_at": "2023-02-02T01:56:51.000Z", "text": "amigo oculto jugabival o ponto alto do dia s\u00e9rio como sou feliz", "id": "1620964431864774656"},{"created_at": "2023-02-02T01:34:26.000Z", "text": "cade o amigo oculto do 1372 ?? https://t.co/vJHykcug0h", "id": "1620958791792730112"},{"created_at": "2023-02-02T01:33:16.000Z", "text": "\"ele \u00e9 babaca, ele \u00e9 rid\u00edculo, mas ele \u00e9 gente boa\"\n\nt\u00f4 juntando as frases passivo-agressivas do BBB pro pr\u00f3ximo amigo-oculto", "id": "1620958497360990209"},{"created_at": "2023-02-02T01:01:49.000Z", "text": "berrooooio!!! hahahahaha GANHEI DE AMIGO OCULTO NO NATAL https://t.co/ZAGTg335pt", "id": "1620950581551706114"},{"created_at": "2023-02-02T00:28:43.000Z", "text": "ROM\u00c1RIO, VOTO SECRETO \u00c9 DE QUEM N\u00c3O TEM CAR\u00c1TER. \nPOR CASO \u00c9 AMIGO OCULTO? OU GATO NA TUBA? MOLEQUE!! https://t.co/wPJ71NMJ2O", "id": "1620942254226685952"},{"created_at": "2023-02-02T00:07:10.000Z", "text": "O \u00f4nibus da ro\u00e7a era assim. Rolava at\u00e9 amigo oculto https://t.co/Thk6s2eInS", "id": "1620936830530232320"},{"created_at": "2023-02-01T23:53:01.000Z", "text": "@56_soaress @mrsmaryneves o que eu pego faz amigo oculto no fim do ano", "id": "1620933268852940803"},{"created_at": "2023-02-01T23:33:26.000Z", "text": "@Ti4oNoveleiro Que inclusive ele matou a pau, morria de medo desse filme quando eu era crian\u00e7a, mas parando pra pensar, a Dakota Fanning que \u00e9 um Mackaulin 2.0 fez O AMIGO OCULTO, ap\u00f3s v\u00e1rias com\u00e9dias", "id": "1620928340717875200"},{"created_at": "2023-02-01T22:47:15.000Z", "text": "N\u00e3o ganhando no amigo oculto de fam\u00edlia ou do trabalho est\u00e1 \u00f3timo https://t.co/kIElYi1utt", "id": "1620916716401483776"},{"created_at": "2023-02-01T22:41:38.000Z", "text": "@eylanefeitosa Sendo muito sincero!!!!\n\nAmigo Oculto", "id": "1620915304804016129"},{"created_at": "2023-02-01T21:56:33.000Z", "text": "gastei meu dinheiro todo e descobri q tem amigo oculto sexta VIADO", "id": "1620903960008876033"},{"created_at": "2023-02-01T15:35:36.000Z", "text": "Victoria descrevendo o amigo oculto \u201c \u00e9 uma pessoa mt inteligente\u201d, corta pra fabricio e duda se olhando e falando \u201c \u00c9 O VELLOSO\u201d KKKKKKKK", "id": "1620808090806546437"},{"created_at": "2023-02-01T14:49:36.000Z", "text": "Ganhei esse no amigo oculto e achei que n\u00e3o ia ler t\u00e3o cedo pois muito pesado mas a\u00ed entrei num clube do livro que esse \u00e9 o livro de fevereiro e to vivendo uma experi\u00eancia bizarra de leitura e choro que n\u00e3o tinha vivido ainda https://t.co/TsjLALUoT3", "id": "1620796512019312640"},{"created_at": "2023-02-01T13:15:52.000Z", "text": "@yastropicana Queria saber quem inventa essas regras: \nrabanada s\u00f3 em fim de ano\nAmigo oculto tbm entre outras", "id": "1620772923928887299"},{"created_at": "2023-02-01T13:04:55.000Z", "text": "@SenadorKajuru T\u00e1 a\u00ed mais um pol\u00edtico que n\u00e3o ganha mais nada nem em amigo oculto. Vergonha demais desse cara", "id": "1620770169923706883"},{"created_at": "2023-02-01T12:31:13.000Z", "text": "A Churrasqueira Est\u00e1 Acesa, E O Card\u00e1pio Variado!\n1\u00b0 Dia A Estrada;\n2\u00b0 Helic\u00f3ptero;\n \nE Hoje \u00c9 A Foto No Instagram, Com Um Amigo Oculto.\n\nA Se Fosse Bolsonaro! https://t.co/7Xjd7q0O3f", "id": "1620761688839684096"},{"created_at": "2023-02-01T03:32:51.000Z", "text": "Kkkkkkkk a menina do trabalho q me tirou no amigo oculto me deu um pacote de camisinha junto com a roupa q me deu, q \u00f3dio kkkkkkkkk", "id": "1620626203697872896"},{"created_at": "2023-02-01T03:19:41.000Z", "text": "Ganhei esse moletom com estampa do quadro \u201cO nascimento de venus\u201d no amigo oculto do trabalho e eu simplesmente amei https://t.co/hkac4RKgpC", "id": "1620622890529067009"},{"created_at": "2023-02-01T03:06:24.000Z", "text": "Rolou o amigo oculto da empresa.\nDei o presente que meu amigo oculto queria. E o cara \u00e9 meu parceiro de trampo, da minha equipe, ent\u00e3o foi suave.", "id": "1620619548436340736"},{"created_at": "2023-02-01T01:56:51.000Z", "text": "lembrando de quando a mina me tirou no amigo oculto e aproveitou o tempo q ela tinha pra falar de mim pra me esculachar", "id": "1620602046981492736"},{"created_at": "2023-02-01T01:41:00.000Z", "text": "@zSenshi_Sama quando eu era do pr\u00e9, teve um amigo oculto na p\u00e1scoa na minha escola no recreio, e meu amigo oculto me tirou e eu tirei ele, eu dei uma caixa de bombom da nestle pra ele, e ele me deu uma barra de chocolate ruim pra caralho de marca desconhecida e com gosto de sab\u00e3o +", "id": "1620598056432574466"},{"created_at": "2023-02-01T00:36:39.000Z", "text": "Coloquei o chinelo que ela me deu no amigo oculto.. em falar em amigo oculto, ela estava t\u00e3o ansiosa com aquele amigo oculto, mais do que todo mundo inclusive. E ela me tirou e falou que era Deus no c\u00e9u e eu na terra. S\u00f3 a gente sabia o quanto t\u00ednhamos conex\u00e3o", "id": "1620581863097253888"},{"created_at": "2023-01-31T23:41:03.000Z", "text": "@CaioBellandi T\u00e1 disc\u00edpulo do Prof Simas, Bellandi??? Kkkkk\nFicou \u00f3timo! \nE em tempo: Lembro como se fosse hoje desse desfile.\n\u00c9poca em que a fita cassete das Escolas de Samba s\u00f3 saia do r\u00e1dio gravador para dar lugar as do Roberto Carlos (todas obviamente trocadas no Amigo Oculto da fam\u00edlia)", "id": "1620567868122488835"},{"created_at": "2023-01-31T23:02:56.000Z", "text": "Em 2020, Juscelino direcionou R$ 2,9 milh\u00f5es do or\u00e7amento secreto para a empresa do amigo oculto. O dinheiro foi liberado no final do ano passado, pouco antes de Juscelino ser escolhido pelo presidente Lula para chefiar a pasta das Comunica\u00e7\u00f5es. https://t.co/pqcyVL0V6r", "id": "1620558278538444800"},{"created_at": "2023-01-31T22:56:54.000Z", "text": "@Astronomiaum Todos s\u00e3o sensacionais e admir\u00e1veis, mas Einstein \u00e9 \u00eddolo desde a minha inf\u00e2ncia. Eu cheguei a pedir um quadro com a famosa foto dele mostrando a l\u00edngua num amigo oculto nos tempos de col\u00e9gio (a pessoa que me tirou n\u00e3o conseguiu encontrar e me deu uma camisa polo). \ud83d\ude2d https://t.co/x0SsvSxZmA", "id": "1620556759206330369"},{"created_at": "2023-01-31T21:27:03.000Z", "text": "@PareceVeridicoK Nunca gostei de fazer amigo oculto\nS\u00f3 recebia coisa ruim...", "id": "1620534146862022656"},{"created_at": "2023-01-31T20:34:34.000Z", "text": "muito boa a cena do amigo oculto no especial de natal de sw me mijo de rir", "id": "1620520938185068545"},{"created_at": "2023-01-31T17:02:14.000Z", "text": "Virou amigo oculto essa porra? Din\u00e2mica \u00e9 o caralho!", "id": "1620467506212409345"},{"created_at": "2023-01-31T16:40:43.000Z", "text": "@MissRedCavill Amigo oculto da creche. Amiga ganhou fantoches, ela um fog\u00e3o.", "id": "1620462088094375936"},{"created_at": "2023-01-31T13:39:23.000Z", "text": "Tava contando pra minha m\u00e3e que uma prima ganhou a biblia da mulher de presente de amigo oculto no natal. \nA minha m\u00e3e: lembra quando voc\u00ea ganhou b\u00edblia e jogou fora?", "id": "1620416457355169792"},{"created_at": "2023-01-31T13:16:37.000Z", "text": "era s\u00f3 um amigo oculto de ifood online, sabe...", "id": "1620410727889797120"},{"created_at": "2023-01-31T12:51:59.000Z", "text": "@Mauker cestas e amigo oculto, check!", "id": "1620404527995457536"},{"created_at": "2023-01-31T10:42:41.000Z", "text": "@vanvancarvalho_ @chefdangalhardo Se tivesse ido no nosso amigo oculto, teria comido... hehehe", "id": "1620371988983472128"},{"created_at": "2023-01-31T05:03:16.000Z", "text": "Eu tenho trauma de amigo oculto", "id": "1620286568962588672"},{"created_at": "2023-01-31T04:15:16.000Z", "text": "Bateu uma saudade do dia do amigo oculto dos sabaders \ud83d\ude2d", "id": "1620274492483473409"},{"created_at": "2023-01-31T02:50:01.000Z", "text": "Sonhei essa noite que tava dentro do filme amigo oculto, vi o filme a 20 anos atr\u00e1s, algu\u00e9m me explica se \u00e9 normal isso?", "id": "1620253037733515264"},{"created_at": "2023-01-31T00:35:12.000Z", "text": "agitando o amigo oculto de P\u00e1scoa com as friends \ud83e\udef6\ud83c\udffd", "id": "1620219108997599232"},{"created_at": "2023-01-30T23:14:16.000Z", "text": "Mais um/uma mascote p tropa!!!! \u2764\ud83e\udd7a\nAno que vem o amigo oculto vai ser das crian\u00e7as haha. \nJ\u00e1 amo esse nen\u00e9m.", "id": "1620198741369327620"},{"created_at": "2023-01-30T23:06:23.000Z", "text": "Lewis me falando que eu tirei ele no amigo oculto https://t.co/u0b1TMn0Nl", "id": "1620196756485988352"},{"created_at": "2023-01-30T18:32:15.000Z", "text": "fazendo a embalagem pra enviar o pc do amigo oculto vai ficar tao bonitinho (eu acho", "id": "1620127769903665153"},{"created_at": "2023-01-30T17:34:53.000Z", "text": "O grupo do amigo oculto j\u00e1 virou grupo de rol\u00ea, j\u00e1 estamos querendo pega uma piscina m\u00eas q vem e agora queremos ir no rod\u00edzio.", "id": "1620113331871965185"},{"created_at": "2023-01-30T15:23:59.000Z", "text": "povo do trabalho querendo fazer amigo oculto gente eu nao tenho dinheiro \ud83d\ude16", "id": "1620080391691571200"},{"created_at": "2023-01-30T14:40:00.000Z", "text": "Assim como eu ganhei no amigo oculto eu tamb\u00e9m presenteei!!! E eu tirei o @naconaul \u00c9 n\u00f3is Luan!!! https://t.co/nmVmB4Agiz", "id": "1620069320759078913"},{"created_at": "2023-01-30T13:45:18.000Z", "text": "@rafaelmenezesrj T\u00f4 com medo de ser convidado pra algum amigo oculto \ud83d\ude05", "id": "1620055555011395584"},{"created_at": "2023-01-30T13:29:24.000Z", "text": "fui dormir 4 da manh\u00e3 e tive q dormir de luz acesa e ouvindo m\u00fasica pq inventei de assistir amigo oculto e \u201cCharlie, Charlie\u201d n\u00e3o saia da minha cabe\u00e7a lkkkkkk", "id": "1620051556182937600"},{"created_at": "2023-01-30T13:23:45.000Z", "text": "Bolinha me tirou ontem no amigo oculto", "id": "1620050131646320642"},{"created_at": "2023-01-30T12:17:46.000Z", "text": "Muito triste com a not\u00edcia da morte do Jos\u00e9 Lino Souza Barros. Trabalhamos juntos na @itatiaia e j\u00e1 tive o privil\u00e9gio de sair com ele no nosso amigo oculto por duas vezes, claro, o presente sempre foi CDs dos Beatles. Descanse em paz querido Z\u00e9 Lino.", "id": "1620033528523259905"},{"created_at": "2023-01-30T12:00:36.000Z", "text": "@WonderMafe @dougdesimone vou te dar no pr\u00f3ximo amigo oculto", "id": "1620029205810667527"},{"created_at": "2023-01-30T11:47:42.000Z", "text": "vamo fazer amigo oculto de capinha de celular amo mt", "id": "1620025961420042240"},{"created_at": "2023-01-30T04:49:10.000Z", "text": "@MaisAcido @camidosreis Pra piorar ele tem o carisma de um banco de madeira. Uma cara de cu eterna, tadinho...\n\nMas arrasou no presente do amigo oculto do fant\u00e1stico.", "id": "1619920635832180736"},{"created_at": "2023-01-30T02:59:09.000Z", "text": "@euclarice \u00c9 o amigo oculto rouba presente", "id": "1619892948115808258"},{"created_at": "2023-01-30T02:20:17.000Z", "text": "@isabelapraado SIMMMMM E O NOSSO AMIGO OCULTO\ud83d\ude2b", "id": "1619883164675227648"},{"created_at": "2023-01-29T23:58:24.000Z", "text": "Simplesmente ganhei um pingente de ouro com a inicial do meu nome em uma plaquinha de amigo oculto, minha cunhada arrasaaaaaa \ud83e\udd79\ud83e\udd70", "id": "1619847461308350464"},{"created_at": "2023-01-29T23:57:31.000Z", "text": "Deu tempo ir ao shopping, comprar o presente do amigo oculto.\nAinda comprei outra cal\u00e7a preta pra mim que estava na promo\u00e7\u00e3o.", "id": "1619847237252845568"},{"created_at": "2023-01-29T23:49:09.000Z", "text": "eu quero um ano novo, sem amigo oculto, \u00e9 pedir muito?", "id": "1619845131536052225"},{"created_at": "2023-01-29T21:24:11.000Z", "text": "Chegar a Campos, ainda tenho que ir no shopping comprar o presente do amigo oculto da empresa.\nEnrolei a vida toda pra comprar, agora vou comprar em cima da hora", "id": "1619808651799298048"},{"created_at": "2023-01-29T20:14:44.000Z", "text": "po eu simplesmente amei o meu presente de amigo oculto. kizzy simplesmente pica!!!", "id": "1619791171437617154"},{"created_at": "2023-01-29T19:09:57.000Z", "text": "Eu tenho uma lumin\u00e1ria do Inuyasha que ganhei de amigo oculto e fica na sala.\n\nA\u00ed meu pai perguntou: Que bicho \u00e9 esse?\nMinha m\u00e3e: Ah! \u00c9 o Naruto cachorro do anime que ela v\u00ea. \ud83d\ude02", "id": "1619774869604024320"},{"created_at": "2023-01-29T19:06:31.000Z", "text": "@NETINHOOFICIAL3 Lembro quando ganhei esse CD no amigo oculto da escola. Na \u00e9poca a febre em toda desta em Bras\u00edlia era Capricho dos Deuses. \n\nMuitos carnavais e micaretas pelo brasil curtindo suas m\u00fasicas. https://t.co/zRS5XAiSN3", "id": "1619774006437249025"},{"created_at": "2023-01-29T17:25:39.000Z", "text": "Depois dessa edit, a parte do amigo oculto nunca mais foi a mesma pra mim kkkkkkk #MinhaM\u00e3e\u00c9UmaPe\u00e7a3  https://t.co/VNkz08etUl", "id": "1619748621309874176"},{"created_at": "2023-01-29T16:30:07.000Z", "text": "@severosnapefics eu li 38 fanfics, adm, vou at\u00e9 colocar o post pra quem quiser ir ver quais as fics que eu li (e recomendo todas).\nmas vou dar destaque para as leituras do amigo oculto nosso, li todas as hist\u00f3rias e amei demais. esse grupo \u00e9 cheio de gente talentosa \u2665\nhttps://t.co/sN7otnMEuy", "id": "1619734645331091456"},{"created_at": "2023-01-29T15:57:26.000Z", "text": "\u00e9 sim do amigo oculto qur ela est\u00e1 me devendo https://t.co/8bk85ctyTk", "id": "1619726420556808193"},{"created_at": "2023-01-29T15:45:35.000Z", "text": "@laixc L\u00e9o Santana tem amigo oculto \ud83d\ude05", "id": "1619723439996297219"},{"created_at": "2023-01-29T14:25:51.000Z", "text": "Qual tecla SAP do evangeliqu\u00eas voc\u00eas n\u00e3o suportam?\n\nAlguns que eu odeio:\nPraGod = Pagode\nAmigo Revelado = Amigo Oculto\nA\u00e7\u00e3o entre Amigos = Rifa\n\nGente, s\u00e9rio, isso me causa do f\u00edsica hahaha", "id": "1619703374957645825"},{"created_at": "2023-01-29T07:21:55.000Z", "text": "The Gardens Between\n\u00a1Te encontr\u00e9! (Plata)\nLiberar al amigo oculto del jard\u00edn. #PS4share https://t.co/tSdBDOem5Y https://t.co/shiMI091S4", "id": "1619596688368308224"},{"created_at": "2023-01-29T03:42:21.000Z", "text": "Minha melhor amiga me tirou no amigo oculto \ud83d\ude2d\ud83d\ude2d\ud83d\ude2d", "id": "1619541431860994051"},{"created_at": "2023-01-29T02:39:06.000Z", "text": "Melhor do que o grupo do amigo oculto, t\u00e1 sendo a gente no Uber indo pra l\u00e1 kkkkk", "id": "1619525512875098112"},{"created_at": "2023-01-29T00:40:53.000Z", "text": "Fui inventar de participar de um amigo oculto, agora tenho uma roupa de academia feia p cacete q provavelmente nem me serve e n\u00e3o vou ganhar o meu presente pq cancelaram \ud83d\udc96", "id": "1619495763079467011"},{"created_at": "2023-01-28T22:41:06.000Z", "text": "Meu amigo oculto al\u00e9m de dar um presente que era algo que quem me conhece compraria pra mim (ent\u00e3o n\u00e3o errou em nada), fez um discurso da cabe\u00e7a dela que esquentou meu cora\u00e7\u00e3o \ud83e\udd70", "id": "1619465620722188289"},{"created_at": "2023-01-28T20:22:49.000Z", "text": "@77_frota Essa familicia \u00e9 demais.  \u00c9 s\u00f3 filmar o amigo oculto que acaba com tudo", "id": "1619430820816777216"},{"created_at": "2023-01-28T18:05:19.000Z", "text": "Sai do amigo oculto, torci o tornozelo. Pqp, tenho anivers\u00e1rio do meu enteado!", "id": "1619396216395280385"},{"created_at": "2023-01-28T18:04:51.000Z", "text": "Com licen\u00e7a que meu amigo oculto me deu um chinelo do Sasuke \u2764\ufe0f\u2764\ufe0f\u2764\ufe0f\u2764\ufe0f https://t.co/kPTWXgOdui", "id": "1619396099151908865"},{"created_at": "2023-01-28T17:46:31.000Z", "text": "Dia 58 de janeiro: usando o sabonete de marca duvidosa que a Eduarda me deu de amigo oculto \nACABA PELO AMOR DE DEUS", "id": "1619391483257434112"},{"created_at": "2023-01-28T17:12:12.000Z", "text": "@https__me \u00e9 isso a\u00ed que vou te dar no pr\u00f3ximo amigo oculto, pronto", "id": "1619382849597214721"},{"created_at": "2023-01-28T05:03:47.000Z", "text": "Queria q tivesse um amigo oculto em fam\u00edlia q eu ia dar um piru de borracha pra essa \"garota\"", "id": "1619199534751682562"},{"created_at": "2023-01-28T04:05:42.000Z", "text": "hoje \u00e9 o amigo oculto n\u00e9\u2026 e minha cabe\u00e7a t\u00e1 estourando at\u00e9 agora por conta do presente que eu vou dar e com medo da pessoa que eu tirei n\u00e3o gostar\u2026", "id": "1619184918407553025"},{"created_at": "2023-01-28T01:50:54.000Z", "text": "O Thiago Rocha me tirou no amigo oculto da Guar\u00e1! Olha esse deslumbre! HahHAhHA Caralho, muito foda! Amei! Tmj irm\u00e3o!!! https://t.co/4pPbJJINja", "id": "1619150997678604289"},{"created_at": "2023-01-28T01:42:39.000Z", "text": "Presente de Amigo Oculto pro @DenisSMello https://t.co/xGPnQIT5as", "id": "1619148919161884673"},{"created_at": "2023-01-28T01:30:11.000Z", "text": "@apocalicess ai amg no pr\u00f3ximo semestre participa, mto bom!! o dri ainda vai fazer uma intera\u00e7\u00e3o com a galera e amigo oculto com os padrinhos e os intercambistas (al\u00e9m de que vc ganha certificado)", "id": "1619145783919648768"},{"created_at": "2023-01-28T00:53:53.000Z", "text": "Pecados \u2014 Gabs Germano\n(\u2b50\ufe0f - 5.0)\n[Harry Potter] [Amigo Oculto do SSF]\n[SSHG] [oneshot] https://t.co/JNCWOiltLl", "id": "1619136645781143552"},{"created_at": "2023-01-28T00:53:10.000Z", "text": "Um Romance Real \u2014 @jjesskmd \n(\u2b50\ufe0f - 5.0)\n[Harry Potter] [Amigo Oculto do SSF]\n[SSHG] [oneshot] https://t.co/nG32aP0s2I", "id": "1619136467217055745"},{"created_at": "2023-01-28T00:52:16.000Z", "text": "Entre livros e sussurros \u2014 @cruciushoney \n(\u2b50\ufe0f - 5.0)\n[Harry Potter] [Amigo Oculto do SSF]\n[SSHP] [oneshot] https://t.co/A6CFuB5I73", "id": "1619136242456883200"},{"created_at": "2023-01-28T00:51:25.000Z", "text": "BEIJOS NA ESC\u00d3CIA \u2014 @annettenolov \n(\u2b50\ufe0f - 5.0)\n[Harry Potter] [Amigo Oculto do SSF]\n[Severus Snape/Personagem Original Feminina] [oneshot] https://t.co/fiH8pp9qQT", "id": "1619136028320870402"},{"created_at": "2023-01-28T00:41:38.000Z", "text": "@rebequinha_nha e nosso amigo oculto em", "id": "1619133565119389698"},{"created_at": "2023-01-28T00:34:10.000Z", "text": "@/\ud835\udcec\ud835\udcf1\ud835\udcea.\ud835\udcf3\ud835\udcf2 \ud835\ude2f\ud835\ude26\ud835\ude38 \ud835\ude31\ud835\ude30\ud835\ude34\ud835\ude35 \ud835\ude30\ud835\ude2f \u2014 #ASVLGRAM \n\nNoite de amigo doce da equipe de sa\u00fade \ud83c\udfe5\ud83e\udd0d\n\nPor sinal, meu amigo oculto combina muito com o tema! \u00c9 um anjinho gentil, sens\u00edvel e que se dedica de todo o cora\u00e7\u00e3o ao que faz. Espero que goste, @nick_asvl. Me inspiro em voc\u00ea! \ud83e\udd70 https://t.co/FGHtQh2wzU", "id": "1619131687165915137"},{"created_at": "2023-01-27T23:25:55.000Z", "text": "[20:22:03] Prima\u2764\ufe0f: quero d presente um piru de borracha\n [20:22:03] Prima\u2764\ufe0f: de anivers\u00e1rio\n [20:22:04] Prima\u2764\ufe0f: pode anotar a\u00ed\n [20:22:04] Prima\u2764\ufe0f: eu vc e bruna tem q fazer amigo oculto de pica\n [ 20:22:05] Prima\u2764\ufe0f: (de borracha)\n\n???KKKKKKKK", "id": "1619114508777099266"},{"created_at": "2023-01-27T23:14:37.000Z", "text": "meu sonho chegar no final do ano e promover um amigo oculto de horm\u00f4nios", "id": "1619111664619769856"},{"created_at": "2023-01-27T22:53:03.000Z", "text": "@_marichaves vou te deixar forte no pr\u00f3ximo amigo oculto", "id": "1619106237014220800"},{"created_at": "2023-01-27T21:11:06.000Z", "text": "No amigo oculto da empresa o camarada me tirou, teve a cara de pau de ir pra confraterniza\u00e7\u00e3o e n\u00e3o deu o meu presente kkkkkk foi pra confraterniza\u00e7\u00e3o, comeu, bebeu, ganhou presente e n\u00e3o levou o principal. O presente da pessoa. Prazer, @Papelzin97!", "id": "1619080581601705985"},{"created_at": "2023-01-27T19:59:44.000Z", "text": "Falaram tanto do meu presente do amigo oculto que at\u00e9 comprei outro", "id": "1619062623328440321"},{"created_at": "2023-01-27T19:58:58.000Z", "text": "israel no amigo oculto https://t.co/E0QCeFqoVF", "id": "1619062430579187713"},{"created_at": "2023-01-27T19:52:20.000Z", "text": "@luizmuitotop @anninhamfs vou usar aquele q vc me deu no amigo oculto ate ter um p\u00f3s doutoradokkkkkkkkkkkkk", "id": "1619060760738684928"},{"created_at": "2023-01-27T18:28:52.000Z", "text": "O presente do amigo oculto chegou a s\u00e9culos e eu n sei como consegui me segurar, sou muito ansiosa, doida para falar o que comprei kkkk", "id": "1619039752975691776"},{"created_at": "2023-01-27T17:30:55.000Z", "text": "eu e meus amigos fizemos um amigo oculto dai quem me tirou me deu simplesmente O DIARIO DE MISTERIOS DE GRAVITY FALLS!!!!!!!!!!!!!!!!!!!!!! https://t.co/oxKREtErxw", "id": "1619025172622897153"},{"created_at": "2023-01-27T16:33:37.000Z", "text": "Nem sei q horas \u00e9 agora, s\u00f3 sei q vou tomar uma breja. \ud83c\udf7a \nObs. um cara no you tube me deixou feliz, resolvi um b.\u00f3 atrav\u00e9s do video dele. Agradecido amigo oculto, essa breja \u00e9 pra ti. \ud83e\udd1d\ud83d\udc4a\ud83d\udc4f\ud83d\udc4f\ud83d\udc4f\ud83d\udc4f\ud83d\udc4f\ud83d\udc4f\ud83d\udc4f", "id": "1619010751792021504"},{"created_at": "2023-01-27T15:43:30.000Z", "text": "@biachiarotto que lindo vamo fazer um amigo oculto", "id": "1618998137355653122"},{"created_at": "2023-01-27T14:21:00.000Z", "text": "Esse grupo do amigo oculto \u00e9 muito bom kk", "id": "1618977376981094407"},{"created_at": "2023-01-27T13:36:31.000Z", "text": "@JuanReiis2 @PROIBIDAODORIO2 t\u00e1 acabando c o chinelo que ela ganhou no amigo oculto \ud83d\ude2d", "id": "1618966183180656640"},{"created_at": "2023-01-27T11:49:28.000Z", "text": "Imagina estar no metr\u00f4 lendo o livro que voc\u00ea ganhou de amigo oculto no final de ano e algu\u00e9m tirar foto e fazer uma cr\u00edtica social no Twitter \ud83e\udee0 https://t.co/wPZsMrKSt0", "id": "1618939243908452353"},{"created_at": "2023-01-27T04:24:04.000Z", "text": "Chifre \u00e9 igual amigo oculto a gente sempre sabe o do outro kkkkkkkkkkkkkkk cara eu amo o humor do @rodsantannareal", "id": "1618827152375545856"},{"created_at": "2023-01-27T03:55:56.000Z", "text": "Eu quero fazer milh\u00f5es de amigos desapegos pq eh definitivamente em superior ao amigo oculto kkkkkkk", "id": "1618820074219134976"},{"created_at": "2023-01-27T03:08:58.000Z", "text": "31- amigo oculto", "id": "1618808255828074497"},{"created_at": "2023-01-27T02:56:34.000Z", "text": "hoje teve amigo oculto na empresa, E EU GANHEI UMA PORRA DE UMA PA\u00c7OQUINHA DE UM REAL, EU FIQUEI COM VONTADE DE ENFIAR A PORRA DE UMA PA\u00c7OQUINHA DE UM REAL NO CU DA PESSOA QUE ME DEU O CARALHO DA PA\u00c7OQUINHA", "id": "1618805132690591744"},{"created_at": "2023-01-27T01:56:28.000Z", "text": "@ruaanmoraes @isabellasayaof recomenda\u00e7\u00f5es\u2026 vc j\u00e1 at\u00e9 comeu, sua maluca!!!! Pedro levou no amigo oculto kkkkk", "id": "1618790007086665728"},{"created_at": "2023-01-27T01:45:21.000Z", "text": "@GiordanaLube No fim do ano passado, com uma turma de mestrado, propus um amigo oculto cujos presentes eram poesias.", "id": "1618787213088784384"},{"created_at": "2023-01-27T00:48:27.000Z", "text": "At\u00e9 amigo oculto da fam\u00edlia no Natal ele brinca, viaja junto, v\u00e1rias coisas... ate eu mesmo tento ver ele como um primo e acabou pq se ficar pensando muito... kkkk", "id": "1618772890098483200"},{"created_at": "2023-01-27T00:46:05.000Z", "text": "Achei um v\u00eddeo do meu pai de 2016, de um natal que ele ia passar embarcado, e gravou o v\u00eddeo para passar uma mensagem para a fam\u00edlia e para falar do amigo oculto dele (eu) t\u00f4 chorando que nem crian\u00e7a\ud83e\udd0d", "id": "1618772298290561029"},{"created_at": "2023-01-26T23:40:43.000Z", "text": "O pesadelo do amigo oculto \ud83d\udc47 https://t.co/t4M6ktZvBy", "id": "1618755845889859585"},{"created_at": "2023-01-26T23:31:30.000Z", "text": "@TomeLorena @mariajuliaouri1 @dearrrosemary nossa festa de amigo oculto", "id": "1618753525236006915"},{"created_at": "2023-01-26T22:59:07.000Z", "text": "N\u00e3o tem um amigo oculto de firma", "id": "1618745376886120448"},{"created_at": "2023-01-26T21:20:45.000Z", "text": "Todos aqueles terror dos anos 2000 eu vi na \u00e9poca q saiu pra dvd... O chamado, amigo oculto, os 13 fantasmas... Meus pais n tinham a menor no\u00e7\u00e3o, me deixavam ver tudo essas porra\n\nAt\u00e1 a paixao de Cristo eu vi quando crian\u00e7a kkkkk https://t.co/zc6vVeeSYG", "id": "1618720623525769218"},{"created_at": "2023-01-26T19:50:37.000Z", "text": "Ando muito nost\u00e1lgico... os filmes que assisti nas \u00faltimas semanas: American Pie, Premoni\u00e7\u00e3o, Loucademia de Pol\u00edcia, O Amigo Oculto, Todo Poderoso e Efeito Borboleta....", "id": "1618697941950279681"},{"created_at": "2023-01-26T18:50:22.000Z", "text": "Amigo Oculto \u2013 Kevin Nurff, Lucas Pocfit, Malandro and Davi Lucca https://t.co/vxAYTNAqyW", "id": "1618682779566493696"},{"created_at": "2023-01-26T15:54:48.000Z", "text": "@abelhinhastan nossa sim, eu ganhei um cart\u00e3o de presente num amigo oculto e \u00e9 incr\u00edvel o quanto os livros custam beem mais de 70 reais", "id": "1618638594666803201"},{"created_at": "2023-01-26T15:43:25.000Z", "text": "@edu_anttunes eduuu olha quem me tirou no meu primeiro amigo oculto socorrooo https://t.co/1ooVCR9to8", "id": "1618635730947043328"},{"created_at": "2023-01-26T15:35:01.000Z", "text": "@f4bissillage Eu recebi no amigo oculto das minhas amigas, mas t\u00f4 com bloqueio, quero assistir a s\u00e9rie mas quero ler o livro antes \ud83e\udd21", "id": "1618633614371213313"},{"created_at": "2023-01-26T14:42:00.000Z", "text": "@Pessoafelix_08 Voc\u00ea tamb\u00e9m ganhou no amigo oculto", "id": "1618620272994848770"},{"created_at": "2023-01-26T04:12:05.000Z", "text": "e meu presente de amigo oculto do NATAL da minha fam\u00edlia que j\u00e1 foi at\u00e9 comprado e n\u00e3o chegou em mim at\u00e9 hoje ????", "id": "1618461748696317955"},{"created_at": "2023-01-26T00:59:51.000Z", "text": "Tathielle me mata cara \"GANHEI DE AMIGO OCULTO\" \ud83e\udd23\ud83e\udd23\ud83e\udd23\ud83e\udd23\ud83e\udd23\ud83e\udd23\ud83e\udd23\ud83e\udd23\ud83e\udd23\ud83e\udd23\ud83e\udd23\ud83e\udd23\ud83e\udd23\ud83e\udd23\ud83e\udd23", "id": "1618413374123175936"},{"created_at": "2023-01-25T23:01:01.000Z", "text": "depois de mil anos desde q a gente sorteou o amigo oculto finalmente aconteceu qkdhjwwjs mt mt mt mt obg ana pelos pcs\ud83e\udd7a\ud83e\udd7aeu amei tipo MUITO mesmo, vc me deu anima\u00e7\u00e3o de tentar a voltar com a cole\u00e7\u00e3odo hobi :( q a gente fa\u00e7a outros milhoes de amigos ocultos e q deem certo pfv\ud83d\ude4f https://t.co/vdTUU2UV96", "id": "1618383468584669185"},{"created_at": "2023-01-25T22:16:36.000Z", "text": "ngm vai pro amigo oculto e esquece o presente kkkkkkkk \neu devo ser de Marte, n\u00e9 poss\u00edvel", "id": "1618372289200001038"},{"created_at": "2023-01-25T20:37:54.000Z", "text": "MEU PRESENTE DO AMIGO OCULTO DAS JOYNETES JSHDJWJSJSJSJEJS\ud83d\ude2d\ud83d\ude2d\ud83d\ude2d\ud83d\ude2d\ud83d\ude2d O HOBI MIMINDO E A YEJI LARANJINHA https://t.co/SVbQoCsqRn", "id": "1618347453266427904"},{"created_at": "2023-01-25T17:18:07.000Z", "text": "@brom_elisa O g0rd\u00e3o comunista s\u00f3 se criar o minist\u00e9rio dos restaurantes. O nosso querido Haddad, formado em economia pela universidade vozes da minha cabe\u00e7a, n\u00e3o ganha nem presente no  amigo oculto em final de ano. A tartaruga eu passo. A Simone da dupla qte deu errado vai chorar de novo.", "id": "1618297175922061313"},{"created_at": "2023-01-25T17:12:53.000Z", "text": "professora me tirou no amigo oculto kkkkkkkkkk marmelada", "id": "1618295858998702080"},{"created_at": "2023-01-25T16:22:10.000Z", "text": "Ontem, indo visitar a minha amiga Beatriz, fui manobrar a Mando no morro. Perdi o equil\u00edbrio, pulei e deixei ela cair.\n\nEra a Mando arranhada ou minha perna esmagada.\nDevido ao nervosismo, esqueci de fotografar.\n\nMas tamb\u00e9m perdi meu fone de ouvido que ganhei no Amigo Oculto. https://t.co/fzz1RD5eed", "id": "1618283092741062658"},{"created_at": "2023-01-25T13:58:46.000Z", "text": "hoje vai ser a call do amigo oculto das joynetes KWJSHWHSKSOSO sem or, me matar", "id": "1618247008212647936"},{"created_at": "2023-01-25T13:05:04.000Z", "text": "@mspbra E guardar segredo na hora de fazer aquele \u201camigo oculto\u201d de final de ano?", "id": "1618233492349022208"},{"created_at": "2023-01-25T11:21:39.000Z", "text": "na baixada eu lembro quando ia trabalhar de manh\u00e3 pegava o trem pra central 6:30 da manh\u00e3 entrava num vagao que nego ja se conhecia entraga gente em cada esta\u00e7\u00e3o e geral sabia o nome kkk rolava amigo oculto, baralho, lanche bg era de verdade kkk", "id": "1618207464914325505"},{"created_at": "2023-01-25T11:07:42.000Z", "text": "Gastei R$110 reais no amigo oculto e at\u00e9 agr n\u00e3o ganhei nem 1 havaianas de 20 conto, nunca mais participo \ud83d\ude30", "id": "1618203955301076995"},{"created_at": "2023-01-25T07:54:24.000Z", "text": "@moni_child Sim.. eu odeio tanto ser eu.. ainda comprei de amigo oculto pra uma amiga q tinha pedido t\u00e1.. eu s\u00f3 me fodi nesse rol\u00ea.. \ud83d\ude10", "id": "1618155310908329984"},{"created_at": "2023-01-25T06:11:30.000Z", "text": "Acompanhante para o Natal \u2014 @danielateixeira \n(\u2b50\ufe0f - 5.0)\n[Harry Potter] [Amigo Oculto do SSF]\n[SSHG] [oneshot] https://t.co/w29rfhwPg9", "id": "1618129412947611648"},{"created_at": "2023-01-25T06:09:47.000Z", "text": "Sono Sem Sonhos \u2014 @snapewpew \n(\u2b50\ufe0f - 5.0)\n[Harry Potter] [Amigo Oculto do SSF]\n[Severus Snape/Narcissa Malfoy] [oneshot] https://t.co/TDLyalQdbe", "id": "1618128983874482180"},{"created_at": "2023-01-25T06:08:19.000Z", "text": "\u00daltimas Palavras \u2014 @YaoiIsLife99 \n(\u2b50\ufe0f - 5.0)\n[Harry Potter] [Amigo Oculto do SSF]\n[SSHG] [DMHG] [oneshot] https://t.co/x3mZsjoegr", "id": "1618128613626490880"},{"created_at": "2023-01-25T06:07:08.000Z", "text": "Trato Silencioso \u2014 @corcasonserina \n(\u2b50\ufe0f - 5.0)\n[Harry Potter] [Amigo Oculto do SSF]\n[Severus Snape/Remus Lupin] [oneshot] https://t.co/MosgUFWxmG", "id": "1618128315172413442"},{"created_at": "2023-01-25T06:06:25.000Z", "text": "Miss Granger \u2014 @ladymaevebell \n(\u2b50\ufe0f - 5.0)\n[Harry Potter] [Amigo Oculto do SSF]\n[SSHG] [oneshot] https://t.co/Xp783cminY", "id": "1618128133445783552"},{"created_at": "2023-01-25T06:05:45.000Z", "text": "Feliz Natal Snape! \u2014 Lady J\u00e9h\n(\u2b50\ufe0f - 5.0)\n[Harry Potter] [Amigo Oculto do SSF]\n[SSHG] [oneshot] https://t.co/4IBVOUDbbp", "id": "1618127968932622339"},{"created_at": "2023-01-25T06:01:18.000Z", "text": "Monitor Chefe \u2014 @snapenine \n(\u2b50\ufe0f - 5.0)\n[Harry Potter] [Amigo Oculto do SSF]\n[Severus Snape/Lucius Malfoy] [oneshot] https://t.co/8V9HikYVM2", "id": "1618126847539318786"},{"created_at": "2023-01-25T05:58:50.000Z", "text": "Simplesmente Acontece \u2014 Dreamer N\n(\u2b50\ufe0f - 5.0)\n[Harry Potter] [Amigo Oculto do SSF]\n[SSHG] [oneshot] https://t.co/EVvGlZlrZ7", "id": "1618126225997975558"},{"created_at": "2023-01-25T05:58:05.000Z", "text": "If I Was Your Vampire \u2014 @russel_dora \n(\u2b50\ufe0f - 5.0)\n[Harry Potter] [Amigo Oculto do SSF]\n[SSHP] [oneshot] https://t.co/LG1MrYapFL", "id": "1618126040056082432"},{"created_at": "2023-01-25T05:57:14.000Z", "text": "Aberra\u00e7\u00f5es Excitantes \u2014 @dumbygemini \n(\u2b50\ufe0f - 5.0)\n[Harry Potter] [Amigo Oculto do SSF]\n[Severus Snape/Remus Lupin] [oneshot] https://t.co/QnI3tYvPKi", "id": "1618125823600652291"},{"created_at": "2023-01-25T05:53:05.000Z", "text": "Um milagre de Natal \u2014 Crowley Lecter\n(\u2b50\ufe0f - 5.0)\n[Harry Potter] [Amigo Oculto do SSF]\n[SSHG] [oneshot] https://t.co/1jy1ErJYOK", "id": "1618124780351401985"},{"created_at": "2023-01-25T05:50:05.000Z", "text": "Como eu sei que gosto de algu\u00e9m? \u2014 Aline Black\n(\u2b50\ufe0f - 5.0)\n[Harry Potter] [Amigo Oculto do SSF]\n[SSHG] [oneshot] https://t.co/OiHErflue8", "id": "1618124025036963840"},{"created_at": "2023-01-25T03:45:28.000Z", "text": "Yoongi n vai em amigo oculto na coreia e agora que inventar de ir em after party em paris eu vo \u00e9 me m namoral tranquem ele", "id": "1618092662221058048"},{"created_at": "2023-01-25T03:20:29.000Z", "text": "@CiceroSmoke @andiefranco O Amigo Oculto https://t.co/SMf4x5jQ4k", "id": "1618086374900658177"},{"created_at": "2023-01-25T03:03:19.000Z", "text": "Que dor no cora\u00e7\u00e3o, n\u00e3o ta caindo minha ficha q minha tia se foi.. Td hora lembro do amigo oculto, fui amostra minha havaiana p ela td boba e ela pensou q eu tinha dado p ela, ficou t\u00e3o feliz q eu n\u00e3o consegui explicar o q aconteceu e deixei p ela\ud83d\ude1e\ud83d\udda4\ud83e\udd40", "id": "1618082055375716357"},{"created_at": "2023-01-25T03:00:43.000Z", "text": "@tattazinhalima @BrunnoDeMiranda Imagina amigo oculto de natal!", "id": "1618081403534729217"},{"created_at": "2023-01-25T02:37:31.000Z", "text": "@Curyxl @shitpostverdade @Lud_macciotti pensei na hora que eu vi em vc colocando no amigo oculto", "id": "1618075565243928577"},{"created_at": "2023-01-25T01:37:38.000Z", "text": "ele rimando igual a batalha de rimas do amigo oculto", "id": "1618060494371446785"},{"created_at": "2023-01-25T00:43:53.000Z", "text": "Hist\u00f3ria que ningu\u00e9m perguntou: li todos os livros em pdf na tradu\u00e7\u00e3o clandestina antes do livro chegar no Brasil depois ganhei o livro de amigo oculto nunca li e minha m\u00e3e emprestou pra algu\u00e9m que n\u00e3o devolveu at\u00e9 hoje https://t.co/6UNHypgmdg", "id": "1618046965761331201"},{"created_at": "2023-01-25T00:10:29.000Z", "text": "@gabriellCRF1 A camisa que eu te dei de amigo oculto finalmente vai caber \ud83d\ude2d", "id": "1618038562322280449"},{"created_at": "2023-01-24T23:30:55.000Z", "text": "@o_ObaOba @TozzaFla Ganhei uma polo de amigo oculto no Natal. Ficou pequena\u2026fui na loja e troquei pelo manto 3, o \u00fanico q faltava de 22\u2026rs", "id": "1618028604339924992"},{"created_at": "2023-01-24T22:57:02.000Z", "text": "@yanna_terra E eu que sou seu amigo oculto, pq tudo q voc\u00ea marca sua amiga werneck aparece para mim kkkkkkkkkk", "id": "1618020079584808960"},{"created_at": "2023-01-24T22:56:40.000Z", "text": "Eu vejo esse v\u00eddeo e s\u00f3 lembro de mim chorando falando que tinham roubado o chinelo que eu ganhei no amigo oculto KAKSKSKSKSKSKSKE a cacha\u00e7a as vezes humilha https://t.co/LjozKmyrOn", "id": "1618019985619849218"},{"created_at": "2023-01-24T22:30:36.000Z", "text": "Kkkkkk igualzinho a mim quando a Fl\u00e1via me tirou de amigo oculto https://t.co/iFVoDmDANI", "id": "1618013425141153792"},{"created_at": "2023-01-24T21:37:39.000Z", "text": "o amigo oculto das joynetes q t\u00e1 desde o ano passado FINALMENTE vai acontecer", "id": "1618000102119059456"},{"created_at": "2023-01-24T19:48:19.000Z", "text": "nov e dez foram os melhores meses da loja, pessoal recebendo 13, fazendo compras de natal, amigo oculto, presente p fam\u00edlia/amigos, itens pra levar nas viagens, repor o que acabou ao longo do ano... chega janeiro \u00e9 s\u00f3 conta imposto matr\u00edcula pagar a fatura de dezembro... CHEGA!!1", "id": "1617972584297148416"},{"created_at": "2023-01-24T19:47:02.000Z", "text": "J\u00e1 falei aqui que ganhei de amigo oculto um livro em 2013 e hoje em dia ele vale 6 mil conto?", "id": "1617972260761133057"},{"created_at": "2023-01-24T19:38:16.000Z", "text": "Juro affffffff odeio usaram isso como caracter\u00edstica pra mim num amigo oculto e eu nunca esque\u00e7o", "id": "1617970054573993987"},{"created_at": "2023-01-24T19:26:50.000Z", "text": "Comprei o presente do meu amigo oculto e acho que elu vai gostar muito, t\u00f4 animada", "id": "1617967179273744384"},{"created_at": "2023-01-24T16:36:52.000Z", "text": "Eu n\u00e3o tinha como comprar o livro f\u00edsico e n\u00e3o gostava de ler no computador, ent\u00e3o imprimi os 7 primeiros cap\u00edtulos. At\u00e9 que a minha m\u00e3e viu o que eu estava fazendo, pediu de amigo oculto no final de ano no trabalho dela e me deu o livro. \ud83e\udd70 https://t.co/83ovWauSRY", "id": "1617924403572125703"},{"created_at": "2023-01-24T16:15:50.000Z", "text": "ganhei serotonina pra o ano todo com esse amigo oculto \ud83d\ude2d @tata_hell obrigada pelo carinho e por tudo, te amo muito e to toda bobinha com os presentes https://t.co/aAcTiW7xY1", "id": "1617919113858539521"},{"created_at": "2023-01-24T15:54:55.000Z", "text": "Imagina um amigo oculto de livros com todo o booktt kskskskks a bagun\u00e7a que seria pra organizar", "id": "1617913849415610368"},{"created_at": "2023-01-24T15:16:21.000Z", "text": "At\u00e9 hoje eu escrevo cartas, recadinhos, e deixo claro a todas ao meu redor o quanto s\u00e3o importantes pra mim. E, toxicamente, passei a \"obrigar\" meus melhores amigos a me escreverem carta no nosso amigo oculto, se n\u00e3o eu n\u00e3o quero o presente.", "id": "1617904140843364352"},{"created_at": "2023-01-24T12:50:20.000Z", "text": "vi todo mundo ganhar coisa e brinquedo legal e eu fiquei l\u00e1 com os prendedor de roupa + a maletinha da barbie, depois desse dia nunca mais rolou amigo oculto e tamb\u00e9m nunca mais teve fam\u00edlia reunida", "id": "1617867398006329345"},{"created_at": "2023-01-24T12:50:18.000Z", "text": "Teve um natal que aconteceu um amigo/inimigo oculto, eu tava toda feliz porque ia ser o primeiro amigo oculto em fam\u00edlia, a\u00ed foi passando de pessoa pra pessoa e todo mundo tava recebendo um presente legal, at\u00e9 que chegou a pessoa que tinha me sorteado++ https://t.co/7a5HBFcAlq", "id": "1617867389538045952"},{"created_at": "2023-01-24T11:57:38.000Z", "text": "Eu no amigo oculto da outra empresa era s\u00f3 as express\u00f5es dele https://t.co/parlLUopN8", "id": "1617854133998059524"},{"created_at": "2023-01-24T11:46:26.000Z", "text": "amigo oculto em plena ter\u00e7a feira me fode legal \ud83d\ude2a", "id": "1617851316214325250"},{"created_at": "2023-01-24T07:46:46.000Z", "text": "Dia 14 de Fevereiro voc\u00eas tb fazem amigo oculto?", "id": "1617791001900507136"},{"created_at": "2023-01-24T04:53:36.000Z", "text": "@skvvlz T\u00f4 imaginando voc\u00eas fazendo um amigo oculto", "id": "1617747420850589697"},{"created_at": "2023-01-24T04:08:31.000Z", "text": "CEZAR \"AI PRETO\" BLACK\u2122 PURO CARISMA\n\nparece que ta no amigo oculto", "id": "1617736078332682241"},{"created_at": "2023-01-24T04:07:50.000Z", "text": "O Cesar tem aquele esp\u00edrito de amigo oculto no fim do ano haha", "id": "1617735906353631234"},{"created_at": "2023-01-24T03:53:32.000Z", "text": "@celinamesmo Caraca, mem\u00f3ria desbloqueada total. Eu lembro que dei um desse de presente de amigo oculto (em minha defesa foi o que a pessoa pediu).", "id": "1617732308420923396"},{"created_at": "2023-01-24T03:43:50.000Z", "text": "Esse jogo da disc\u00f3rdia t\u00e1 parecendo amigo oculto de empresa.  #bbb23", "id": "1617729864207065089"},{"created_at": "2023-01-24T03:43:33.000Z", "text": "que discurso de amigo oculto do krl KKKKKKKKKKKKKK", "id": "1617729792450912259"},{"created_at": "2023-01-24T03:28:24.000Z", "text": "Cowboy parece que ta dando dica de amigo oculto ahahah #BBB23", "id": "1617725980529000449"},{"created_at": "2023-01-24T03:06:37.000Z", "text": "3 vezes que fazem sorteio para o amigo oculto,ja foi jessica e Jo\u00e3o,quem \u00e9 o proximo?\ud83d\ude02", "id": "1617720500767305728"},{"created_at": "2023-01-24T02:44:52.000Z", "text": "@arthie_art foi amigo oculto de caneca kskdkk\na ideia \u00e9 muito boa mas a execu\u00e7\u00e3o foi horr\u00edvel", "id": "1617715025954885632"},{"created_at": "2023-01-24T02:19:40.000Z", "text": "S\u00e1bado tem o amigo oculto \u2764", "id": "1617708684989304833"},{"created_at": "2023-01-24T01:34:50.000Z", "text": "Tirei no amigo oculto o esposo da mulher que eu gosto \ud83d\ude29 #stardewvalley", "id": "1617697401883750400"},{"created_at": "2023-01-24T01:08:33.000Z", "text": "@luscas Parecendo que ela ia desvendar um amigo oculto na empresa", "id": "1617690788812722176"},{"created_at": "2023-01-24T00:52:58.000Z", "text": "Chorando porque sem querer eu quebrei a minha x\u00edcara que ganhei de amigo oculto", "id": "1617686864118546433"},{"created_at": "2023-01-24T00:42:17.000Z", "text": "Eu t\u00f4 s\u00f3 o poncho nos amigo oculto", "id": "1617684177486483457"},{"created_at": "2023-01-24T00:40:15.000Z", "text": "eu no amigo oculto da empresa kkkkkk", "id": "1617683663554244608"},{"created_at": "2023-01-24T00:31:34.000Z", "text": "Pessoal aqui em casa fica abismado com minha felicidade em ganhar/comprar cabide de roupa. 3 anos pedindo isso no amigo oculto de natal e hoje comprei + 12. Satisfa\u00e7\u00e3o em ver minhas roupas penduradas", "id": "1617681478145683459"},{"created_at": "2023-01-24T00:10:40.000Z", "text": "@Dmaris32226932 Pior n\u00e3o \u00e9 valor monet\u00e1rio e valor sentimental  \"tipo este objeto tem tudo haver com a fulana \"j\u00e1 ganhei presilha de cabelo de amigo oculto que sabe que uso cabelo super curto kkkkkkkk #S\u0131laT\u00fcrko\u011flu  #K\u0131z\u0131lc\u0131k\u015ferbeti", "id": "1617676220271058944"},{"created_at": "2023-01-23T23:32:24.000Z", "text": "Eu nos amigo oculto da vida desde o fundamental sempre ganhando um presente bem inferior ao que eu dava por mais que o pre\u00e7o fosse estipulado.kkkkkkkkk \nParei com essa brincadeira kkkkkk rindo de nervoso mesmo.\n#S\u0131laT\u00fcrko\u011flu\n#K\u0131z\u0131lc\u0131k\u015eerbeti https://t.co/UPDs4ThIKA", "id": "1617666589171810304"},{"created_at": "2023-01-23T22:09:52.000Z", "text": "Amigo oculto fui a primeira a sair porque tinha planos com minhas pessoas \ud83e\udd70\ud83d\ude02. https://t.co/Gj7tSxJFkT", "id": "1617645821264269316"},{"created_at": "2023-01-23T22:02:04.000Z", "text": "@LulaOficial @alferdez @geraldoalckmin @ricardostuckert Lula, voc\u00ea \u00e9 o melhor amigo do Geraldo. Eu tenho certeza que ele vai querer manipular o amigo oculto do ano que vem s\u00f3 pra tirar voc\u00ea, dar um presidente top e fazer um discurso de gratid\u00e3o.", "id": "1617643858145447943"},{"created_at": "2023-01-23T20:20:42.000Z", "text": "odeio amigo oculto e piora qnd voc\u00ea n\u00e3o tem intimidade com ningu\u00e9m", "id": "1617618345930653696"},{"created_at": "2023-01-23T18:20:57.000Z", "text": "AMIGO OCULTO: OUVINTE KAROL BARBOSA ACERTA AMIGO LUCAS LIMA, MARIDO DA SANDY; QUEM VAI ACERTAR O AMIGO DA KAROL HOJE? https://t.co/jt7ufr33At", "id": "1617588209726128132"},{"created_at": "2023-01-23T17:38:32.000Z", "text": "N\u00e3o vejo a hora de dar um iphone de ultima gera\u00e7\u00e3o e um apple watch de amigo oculto no natal", "id": "1617577536841748481"},{"created_at": "2023-01-23T17:02:32.000Z", "text": "@fernandoulrich Sabe aquela sensa\u00e7\u00e3o de injusti\u00e7a quando no amigo oculto voc\u00ea d\u00e1 um presente super legal e caprichado e recebe de volta 2 sabonetes?\n\nEsse seria nossa sensa\u00e7\u00e3o numa prov\u00e1vel moeda \u00fanica com a Argentina.", "id": "1617568477329620993"},{"created_at": "2023-01-23T03:47:39.000Z", "text": "Hoje oficialmente se encerrou o natal para mim\n\n(minha fam\u00edlia finalmente fez o amigo oculto)", "id": "1617368438149873664"},{"created_at": "2023-01-23T03:38:19.000Z", "text": "o presente da @biagramas pra mim de amigo oculto https://t.co/zKmLWbxZkH", "id": "1617366090555826176"},{"created_at": "2023-01-23T01:45:48.000Z", "text": "@Hugaunda sim uma querida camarada me deu de amigo oculto", "id": "1617337772380983297"},{"created_at": "2023-01-22T23:21:14.000Z", "text": "Talento: saber todas as falas de \"Amigo oculto da Akatsuki\".", "id": "1617301390149263361"},{"created_at": "2023-01-22T22:14:15.000Z", "text": "@M4RKFAIRYS Eu namoro com o meu amigo oculto kkkkkkk", "id": "1617284535745654785"},{"created_at": "2023-01-22T21:13:30.000Z", "text": "@caharaujo2 Voc\u00ea me d\u00e1 uma e eu te dou uma tbm kkkkkk amigo oculto de duas pessoas", "id": "1617269245276037121"},{"created_at": "2023-01-22T17:13:49.000Z", "text": "Se levassem o amigo oculto t\u00e3o a serio quanto levam minhas piadas dava certo", "id": "1617208926679846915"},{"created_at": "2023-01-22T17:03:05.000Z", "text": "Eu vi um v\u00eddeo que desbloqueou uma mem\u00f3ria nada a ver kkkkkkkkkkkkk. Teve um amigo oculto na escola e teve um rapaz que recebeu um presente super legal que eu n\u00e3o lembro o que era, mas ele deu uma caixa de bis, que tava aberta e faltando metade dos chocolates, o outro ficou puto", "id": "1617206225673850882"},{"created_at": "2023-01-22T15:42:05.000Z", "text": "Apaixonada nos meus presentinhos de amigo oculto", "id": "1617185842136506370"},{"created_at": "2023-01-22T15:18:25.000Z", "text": "@matosraquel2 O amigo oculto de presentes internacionais \ud83d\ude02", "id": "1617179887160147969"},{"created_at": "2023-01-22T14:57:06.000Z", "text": "Este ano meta \u00e9 meter muito drip pra no amigo oculto a pessoa n\u00e3o me oferecer dress tou cansado \ud83d\ude11, repetir uma vez por m\u00eas", "id": "1617174522750279684"},{"created_at": "2023-01-22T14:47:14.000Z", "text": "a vittoria usando isso pra me descrever no amigo oculto", "id": "1617172040020008961"},{"created_at": "2023-01-22T14:44:24.000Z", "text": "Como que esquece o presente do amigo oculto indo pro amigo oculto??????? Miseric\u00f3rdia", "id": "1617171327030378497"},{"created_at": "2023-01-22T12:23:27.000Z", "text": "completamente apaixonada por algumas havaianas da farm, meu Deus eu n\u00e3o posso!!!!!!!!\nnunca entendi quem n\u00e3o gosta de amigo oculto de havaianas, se eu pudesse teria uma sapateira s\u00f3 de havaianas \ud83e\udd23\ud83d\ude2e\u200d\ud83d\udca8", "id": "1617135854991953921"},{"created_at": "2023-01-22T05:26:12.000Z", "text": "Eu terminei de assistir O Amigo Oculto\nUm filme espetacular, msm eu ja desde o in\u00edcio especulando quem era o Charlie, ent\u00e3o p mim o plot twist foi ela desenvolvido o msm transtorno do pai", "id": "1617030849425444866"},{"created_at": "2023-01-22T03:29:35.000Z", "text": "Kauan me tirou no amigo oculto e me deu duas capa e uma das capas com fotos nossa \u2764\ufe0f\u2764\ufe0f\u2764\ufe0f\u2764\ufe0f\u2764\ufe0f", "id": "1617001504283451393"},{"created_at": "2023-01-22T02:58:04.000Z", "text": "eu e as meninas kpoppers todo ano fazemos amigo oculto e esse ano conseguimos s\u00f3 agora em janeiro, eu comprei presentes lind\u00edssimos \ud83e\udd70", "id": "1616993573387526144"},{"created_at": "2023-01-22T02:29:48.000Z", "text": "@Hylert21 essas parada de amigo oculto eu realmente nunca gostei :(\ne em minha defesa voc\u00ea foi a que menos ouviu nao de mim !!!", "id": "1616986457243275264"},{"created_at": "2023-01-22T01:52:05.000Z", "text": "Essas confus\u00f5es de amigo oculto t\u00e3o at\u00e9 que me fazendo rir bastante", "id": "1616976968301297665"},{"created_at": "2023-01-22T01:43:23.000Z", "text": "https://t.co/H39doZnikE\n\nSe Shakira lan\u00e7a a m\u00fasica em dezembro o meu amigo oculto seria mais caro\u2026 o tanto de Casio que eu ia entregar. Tomara que a rapaziada acate o papo!!! Intelig\u00eancia p\u00f4", "id": "1616974775896743936"},{"created_at": "2023-01-22T00:38:21.000Z", "text": "se eu ganhar presente bosta nesse amigo oculto eu me mato na frente da pessoa", "id": "1616958410804662274"},{"created_at": "2023-01-22T00:33:30.000Z", "text": "SIMPLESMENTE APAIXONADA NO MEU PRESENTE DE AMIGO OCULTO DE MEMBROS DA @capardini \ud83d\ude0d https://t.co/qKeDdVjWTO", "id": "1616957191172284419"},{"created_at": "2023-01-21T23:13:04.000Z", "text": "@anagendorf_ @musadosmeme @afafafafafav @daniivince @Alicerafaelar @zahatake @joaoplribeiro05 A diferen\u00e7a \u00e9 que eu mato cada uma se esse amigo oculto nao acontecer", "id": "1616936946869174272"},{"created_at": "2023-01-21T22:20:43.000Z", "text": "Todo amigo oculto pra mim \u00e9 assim: minha amiga oculta \u00e9 fofa, meiga, doce, linda (\u2026) ent\u00e3o N\u00c3O sou EU! Kkkkk", "id": "1616923776251305986"},{"created_at": "2023-01-21T22:20:02.000Z", "text": "isso me fez lembrar de quando no amigo oculto o pepe falou que a pessoa q ele tirou seria filha do megamente com o sid (era eu https://t.co/MfxywGphzi", "id": "1616923600761634817"},{"created_at": "2023-01-21T21:15:29.000Z", "text": "N\u00e3o vou nem ficar nesse amigo oculto muito tempo, estou morta de sono", "id": "1616907358772289536"},{"created_at": "2023-01-21T20:59:05.000Z", "text": "@CarvalhoBravo Amigo oculto de rem\u00e9dio? Kkkkkk\nA gente morre e n\u00e3o v\u00ea de tudo\ud83d\ude05\ud83e\udd23\nObrigado pela dica!", "id": "1616903229937164291"},{"created_at": "2023-01-21T20:47:32.000Z", "text": "encontrei a carta que eu fiz p amigo oculto, achei at\u00e9 q tivesse jogado fora", "id": "1616900325180428291"},{"created_at": "2023-01-21T20:46:47.000Z", "text": "@OpBrasilia N\u00e3o sei do seu hist\u00f3rico, mas Ritalina 10mg. Ali\u00e1s, se vc for jovem, consegue f\u00e1cil. Tem at\u00e9 amigo oculto de rem\u00e9dio. \ud83e\udd2a\ud83e\udd2a\ud83e\udd2a", "id": "1616900137325940736"},{"created_at": "2023-01-21T18:26:14.000Z", "text": "@farinhaclara Fui ajudar a minha irm\u00e3 a escolher presente de amigo oculto e ela \u00e9 est de Med Vet a\u00ed ela fez uma caneca pra amiga escrito Dra. Fulana e elas t\u00e3o indo pro segundo per\u00edodo a\u00ed ela me perguntando \" ela vai amar n\u00e9 , n tem problema?\" E eu claro que vai t\u00e1 profetizando!!! +++", "id": "1616864763891294209"},{"created_at": "2023-01-21T18:05:52.000Z", "text": "\u2728desenho que fiz meio na correria pro meu grande amigo @ChavoArts, pro nosso amigo oculto desse ano https://t.co/YKvcfSTdHl", "id": "1616859639949164545"},{"created_at": "2023-01-21T18:04:31.000Z", "text": "doida pra saber o que vou ganhar do meu amigo oculto kkkk", "id": "1616859297920520193"},{"created_at": "2023-01-21T17:31:26.000Z", "text": "Arte que fiz de presente de amigo oculto pro kingo @mangaleao \ud83d\udc9b https://t.co/IKYaY70C1K", "id": "1616850972633972736"},{"created_at": "2023-01-21T17:27:10.000Z", "text": "Primeira arte do ano \u00e9 um desenho que fiz de amigo oculto pra @lenassauro \u2728 https://t.co/Iw5QNtvWgP", "id": "1616849900477747202"},{"created_at": "2023-01-21T14:49:26.000Z", "text": "Ontem descobri que quase ganho um presente de friends no amigo oculto gra\u00e7as a Deus puderam evitar essa trag\u00e9dia \ud83d\ude4f\ud83d\ude4f\ud83d\ude4f\ud83d\ude4f\ud83d\ude4f", "id": "1616810204385144834"},{"created_at": "2023-01-21T14:45:44.000Z", "text": "Esse livro \u00e9 poesia pura! Todo mundo deveria ler, real. Valorizem nossos escritores! Presente da @amandavqueen de amigo oculto de fim de ano &lt;3 #tortoarado #itamarvieirajunior  #bookstagram #booklover #bookworm https://t.co/hXq1FvPtjW", "id": "1616809275711520772"},{"created_at": "2023-01-21T12:35:24.000Z", "text": "@KaKaminaga @bullsbrasil Tbm estou nessa meta a\u00ed.\nComprei uma para um amigo oculto do Boston da edi\u00e7\u00e3o especial e achei a camisa muito fiel a realidade, a\u00ed vou fazer a gentileza de comprar uma para mim tbm.", "id": "1616776475121696772"},{"created_at": "2023-01-21T06:39:01.000Z", "text": "At\u00e9 agora conversando com a Day em liga\u00e7\u00e3o sobre o amigo oculto da empresa \ud83d\ude43", "id": "1616686786104774656"},{"created_at": "2023-01-21T05:55:41.000Z", "text": "Eu tenho uma vontade gigantesca de organizar minhas amigas e alugar um motel com banheira, fazer uma festinha s\u00f3 com a gente  e no meio disso tudo fazer um amigo oculto de lingerie e acess\u00f3rios( er\u00f3ticos)", "id": "1616675883904794625"}]