[{"tweets_quantity": 243},{"created_at": "2023-02-09T00:55:43.000Z", "text": "@melnasc_ Tem a op\u00e7\u00e3o de Prato feito. Voc\u00ea escolhe , a mo\u00e7a serve e paga 22,00. Sempre fa\u00e7o isso", "id": "1623485761600233472"},{"created_at": "2023-02-08T23:24:11.000Z", "text": "usou essa palavra pra nao falar que \u00e9 prato feito", "id": "1623462727317393412"},{"created_at": "2023-02-08T23:04:16.000Z", "text": "Isso msm puta, continua dando em cima de gente comprometidakakakj prato feito", "id": "1623457716764131330"},{"created_at": "2023-02-08T21:03:55.000Z", "text": "Quer ganhar um brinde exclusivo do programa #MinhaM\u00e3eCozinhaMelhorQueASua? Ent\u00e3o vem  adivinhar qual o prato preferido do Edu Rodrigues!\n\n\u2705 Dica de hoje:\"\u00c9 um prato feito com farinha de milho\". E a\u00ed, j\u00e1 tem algum palpite?\n\nO regulamento completo no site https://t.co/TrXyZuUoFp https://t.co/55fhqjO793", "id": "1623427429464170498"},{"created_at": "2023-02-08T20:32:30.000Z", "text": "vai prato feito chama a mam\u00e3e pq eu te chamei de pf\ud83d\ude2d\ud83d\ude2d\ud83d\ude2d\ud83d\ude2d", "id": "1623419521103962112"},{"created_at": "2023-02-08T19:58:27.000Z", "text": "@tinownszete prato feito \ud83e\udd1d\ud83c\udffb", "id": "1623410954351566849"},{"created_at": "2023-02-08T19:50:39.000Z", "text": "@antiparalelo @Moses_Besouchet eu estava falando em Prato Feito", "id": "1623408991391956993"},{"created_at": "2023-02-08T19:48:12.000Z", "text": "Paguei 41 reais em uma comida a quilo que n\u00e3o era quase nada pra descobrir que por 42 poderia ter pedido o prato feito que da pra 2 pessoas kkkkkkkvou me matar", "id": "1623408372904079362"},{"created_at": "2023-02-08T19:38:42.000Z", "text": "@brunovicari @SportsCenterBR @ESPNBrasil @StarPlusCentral Incr\u00edvel como lhe dar prazer criticar o Flamengo! Quando h\u00e1 motivos ent\u00e3o, prato feito! Parab\u00e9ns", "id": "1623405983476187138"},{"created_at": "2023-02-08T18:09:35.000Z", "text": "@JosDonizettiVi3 Est\u00e1 almo\u00e7ando tranquilamente um PF (prato feito), com toda humildade, como quem n\u00e3o deve nada pra PF (policia federal). Cont\u00e9m ironia!", "id": "1623383556197171201"},{"created_at": "2023-02-08T17:37:48.000Z", "text": "pf=prato feito", "id": "1623375557692952587"},{"created_at": "2023-02-08T16:57:12.000Z", "text": "@bruno_roger23 Mais caro que um prato feito", "id": "1623365340917862409"},{"created_at": "2023-02-08T15:30:27.000Z", "text": "logo a marmitex, prato feito do krl? que nojo", "id": "1623343509410312192"},{"created_at": "2023-02-08T15:18:40.000Z", "text": "@JoiaDaLua Se eu n\u00e3o me engano \u00e9 essa hist\u00f3ria mesmo. \u00c9 um prato feito por homens para m\u00e3es ou esposas\nPor isso \u00e9 basicamente uma mistura, eles faziam com o que tinha na geladeira", "id": "1623340544754696192"},{"created_at": "2023-02-08T13:13:58.000Z", "text": "@carlosjordy Ah, e PF no meu tweet signfica por favor. N\u00e3o \u00e9 prato feito e tampouco precisa ficar com medo pois n\u00e3o \u00e9 pol\u00edcia federal.", "id": "1623309162250731520"},{"created_at": "2023-02-08T11:13:02.000Z", "text": "Vai prato feito continua falando q vc pega homem casado", "id": "1623278727428820994"},{"created_at": "2023-02-08T02:53:06.000Z", "text": "@manuelapy_ mulherrrrr, \u00e9 tudo de bom!!!! Se tiver uma saladinha, arroz feij\u00e3o e banana pra mim \u00e9 um prato feito, j\u00e1 fa\u00e7o mais um dia sem carne facil \ud83e\udd17 bom demais, nao vai te arrepender de provar", "id": "1623152916637818881"},{"created_at": "2023-02-08T01:50:51.000Z", "text": "@adss_moreira Amo comida boa caseira e barata. Hoje o meu fave \u00e9 o prato feito, vou visitar esses outros dois \u2764\ufe0f", "id": "1623137248802643970"},{"created_at": "2023-02-08T00:25:58.000Z", "text": "@DaniloGentili @Anitta Pra quem gosta de merda, \u00e9 um prato feito", "id": "1623115886981775360"},{"created_at": "2023-02-07T19:48:03.000Z", "text": "COMIDAS PREFERIDAS!\ud83d\udc40 \nMassa, Prato feito, Churrasco\u2026 Quais os pratos que os atletas do Paulist\u00e3o Sicredi mais gostam? \nComente se voc\u00ea quer ver a parte 2 \ud83c\udf5b \n#FutebolPaulista #Paulist\u00e3oSicredi https://t.co/Qrknkk7dsi", "id": "1623045950502477829"},{"created_at": "2023-02-07T18:42:59.000Z", "text": "Recanto da El\u00f4: A pousada \u00e9 ref\u00fagio para quem quer se conectar com a natureza e o cen\u00e1rio favorece o turismo radical com trilha e pedal com passagem por cachoeiras. A culin\u00e1ria regional \u00e9 um grande atrativo, com  a paella de carro-chefe do lugar, um prato feito no fog\u00e3o a lenha.", "id": "1623029574517784578"},{"created_at": "2023-02-07T18:10:39.000Z", "text": "@CamargoDireita pf trabalhando para o stf. Tenho certeza que quem faz esse servi\u00e7o no judici\u00e1rio \u00e9 o oficial de justi\u00e7a. Mas tudo bem prato feito \u00e9 pra isso e muito mais", "id": "1623021436494352386"},{"created_at": "2023-02-07T17:15:19.000Z", "text": "@isguarnieri O que tinha no prato feito?", "id": "1623007512185167873"},{"created_at": "2023-02-07T17:00:02.000Z", "text": "Tou peidando sem parar aqui no consultorio da medicakkkkkkkkkk acho q o prato feito q eu comi agr pouco n caiu bem kkkkkkkkk", "id": "1623003666893484037"},{"created_at": "2023-02-07T15:56:35.000Z", "text": "O ruim de trabalhar na Savassi \u00e9 que um prato feito \u00e9 25 reais. N\u00e3o tem quem aguente.", "id": "1622987697051648001"},{"created_at": "2023-02-07T13:20:53.000Z", "text": "Comeria um almo\u00e7o preparado por esses humildes vorts ein comeria um prato feito com amor por esses velhos \n\nteria coragem de comer um rango cozinhado por esses meninos https://t.co/Js62CNjdnU", "id": "1622948516325646337"},{"created_at": "2023-02-07T12:54:45.000Z", "text": "eu amassaria um prato feito agora mesmo, 9h54  da manh\u00e3", "id": "1622941939241742336"},{"created_at": "2023-02-07T12:27:47.000Z", "text": "@0800FABI Eu fiz um dicion\u00e1rio gauch\u00eas - carioqu\u00eas quando me mudei pro Sul.\n\nAfud\u00ea: Quer dizer que algo \u00e9 muito bom, legal\n\nAlcan\u00e7ar:  pegar algo pra pessoa \n\n\u00c0 la minuta: Prato Feito (PF) \n\n\"Arrec\u00e9m\": ainda agora, agora h\u00e1 pouco\n\nChavear: trancar a porta (+)", "id": "1622935151364775937"},{"created_at": "2023-02-07T11:25:00.000Z", "text": "@moreiraviw PF, prato feito \u00e9 talvez a escolha mais inteligente", "id": "1622919351882973190"},{"created_at": "2023-02-07T08:48:13.000Z", "text": "@izzynobre Uma coisa revoltante tamb\u00e9m \u00e9 que o brasileiro n\u00e3o valoriza o prato feito, a cerveja super gelada, picanha no churrasco e chinelo havaianas. \n\n\u00c9 muito bom, mas por ser 100% brasileiro muitos n\u00e3o gostam. Fico revoltado.", "id": "1622879894920220672"},{"created_at": "2023-02-07T07:09:06.000Z", "text": "@GabyLabree Samara Joy venceu por ser ela mesma e cantar.\nAnitta perdeu por ser ela mesma e n\u00e3o cantar, mas vulgarizar.\nBem feito, prato feito kkk", "id": "1622854954279919616"},{"created_at": "2023-02-07T06:40:48.000Z", "text": "@paulobilynskyj1 Olha n\u00e3o confio nem em pt e t\u00e3o pouco e pf. Um \u00e9 molusco o outro \u00e9 prato feito. Um manda o outro implanta se n\u00e3o encontra. J\u00e1 viu eles na duana. Ent\u00e3o. Boa noite", "id": "1622847829939986432"},{"created_at": "2023-02-07T05:27:21.000Z", "text": "@BealtifulSoraya @accoun_fan Casquinha? Um prato feito. \ud83d\ude01", "id": "1622829346749644800"},{"created_at": "2023-02-07T02:50:51.000Z", "text": "@DucaTambasco Ah\u2026 vc nao conhece o grande PF (prato feito) da cidade! Hehe", "id": "1622789962448994311"},{"created_at": "2023-02-07T01:55:41.000Z", "text": "@calazans_rei \u00c9 um prato feito da folha da mandioca (taioba), onde as folhas s\u00e3o lavadas pro veneno sair e cozidas at\u00e9 se tornar uma das coisas mais gostosas do mundo. Leva v\u00e1rias carnes tbm", "id": "1622776077625032704"},{"created_at": "2023-02-06T23:26:56.000Z", "text": "@Leonardoaqrz @nikolas_dm Pra quem gosta de chorume tu tem um prato feito \ud83d\ude18", "id": "1622738642367131655"},{"created_at": "2023-02-06T23:13:10.000Z", "text": "Vontade de comer um prato feito com batata frita e bife", "id": "1622735179461656576"},{"created_at": "2023-02-06T21:24:44.000Z", "text": "Eles querem \u00e9 saber do acordo !! Tamb\u00e9m chamam de \u201cprato feito\u201d! https://t.co/BOs1RUhiEm", "id": "1622707889826668545"},{"created_at": "2023-02-06T20:24:31.000Z", "text": "@LevithTheZ Prato feito?", "id": "1622692736079118336"},{"created_at": "2023-02-06T18:17:53.000Z", "text": "PF = Prato Feito! Mais nada! https://t.co/erIlNcpJf1", "id": "1622660867463553027"},{"created_at": "2023-02-06T18:14:27.000Z", "text": "Voc\u00ea n\u00e3o se sentir confort\u00e1vel usando uma roupa \u00e9 prato feito pra gente sem no\u00e7\u00e3o vir falar merda jesus christ", "id": "1622660005185953795"},{"created_at": "2023-02-06T17:13:38.000Z", "text": "@julyaBalbinotti Prato feito kkkkkk", "id": "1622644698937425938"},{"created_at": "2023-02-06T16:21:13.000Z", "text": "vixx, te chamou de prato feito kkkkkkk", "id": "1622631510170796035"},{"created_at": "2023-02-06T16:11:02.000Z", "text": "passei em frente a um restaurante de prato feito e meu deus que vontade de pegar uma batata frita do prato de algu\u00e9m e sair correndo", "id": "1622628948315078656"},{"created_at": "2023-02-06T15:53:15.000Z", "text": "@C9VAL Any salgado, hot dog (way better than American hot dog), pastel, prato feito", "id": "1622624470518169611"},{"created_at": "2023-02-06T15:43:21.000Z", "text": "Pq n\u00e3o entendem meu gosto por almo\u00e7ar em restaurantes simplesmente da regi\u00e3o? \ud83d\ude2d\n\nUm prato feito com batata frita por 15 reais \u00e9 estouro demais", "id": "1622621980997431300"},{"created_at": "2023-02-06T15:15:21.000Z", "text": "@tavares_advg Acorde.  !!! \nA PF prato feito tem esses meninos da foto como amiguinhos. !", "id": "1622614933019013121"},{"created_at": "2023-02-06T14:54:24.000Z", "text": "IMAGINE SE A PF (MAIS PARECE PRATO FEITO) FOSSE T\u00c3O VALENTE CONTRA TRAFICANTES? https://t.co/1Wv4uWvLWd", "id": "1622609660799860736"},{"created_at": "2023-02-06T14:38:26.000Z", "text": "@robertacmrg Mileto, op\u00e7\u00e3o de kilo ou prato feito dentro da realidade", "id": "1622605644233670656"},{"created_at": "2023-02-06T13:38:43.000Z", "text": "10:30 ainda e por mim eu batia 2 prato feito FACIL", "id": "1622590613240651783"},{"created_at": "2023-02-06T13:24:02.000Z", "text": "O prato feito aumentou pra 20 reais, n se pode ser feliz nesse mundo", "id": "1622586921032507392"},{"created_at": "2023-02-06T12:51:40.000Z", "text": "\u00c9 simplesmente um prato feito, e t\u00e1 no est\u00e1dio por apenas 15z\u00e3o\n\nMandava pra dentro sem piedade https://t.co/6kvLW3Wmb6", "id": "1622578774599499777"},{"created_at": "2023-02-06T12:44:21.000Z", "text": "Quem s\u00e3o guskey  e Gustavo  / key Alves votem muito  para #foratina  verificados  biscoiteiros  e p\u00e1ginas de fofoca  s\u00e3o contra guskey  Gustavo e key , tina ficando  vai com tudo contra eles   e vai ser prato feito se Gustavo  e/ou cair no pared\u00e3o  #bbb23 @bbb @guskeymoments", "id": "1622576933165752320"},{"created_at": "2023-02-06T11:04:40.000Z", "text": "Acabou as NARRATIVAS sobre o cart\u00e3o corporativo do Bolsonaro.\nAs redes sociais mostraram que o gasto com o cart\u00e3o numa pastelaria em Roraima.\nFoi com prato feito para centena de pessoas pobre.\nLula vai comprar sem lota\u00e7\u00e3o.\nSer\u00e3o milh\u00f5es ROUBADOS https://t.co/QZ7ByXFQgN", "id": "1622551847260024834"},{"created_at": "2023-02-06T05:03:49.000Z", "text": "@TasteAtlas T\u00e1 de brincadeira garotinho, como que esse prato feito do bandej\u00e3o da UNIRIO bateu a gloriosa picanha pqp", "id": "1622461036904300546"},{"created_at": "2023-02-06T01:52:15.000Z", "text": "ser\u00e1 que \u00e9 buffet livre no grammy? ou prato feito?", "id": "1622412827246956544"},{"created_at": "2023-02-06T00:05:22.000Z", "text": "L\u00e1 se vai o marketing do iFood com doa\u00e7\u00f5es de prato feito da cidade. Coordena\u00e7\u00e3o de pol\u00edticas p\u00fablicas se d\u00e1 pelo Estado, n\u00e3o por caridade do \u201clivre mercado\u201d.\n\nhttps://t.co/d8P3vczMy7 https://t.co/YLdsGwby3e", "id": "1622385929385119744"},{"created_at": "2023-02-06T00:04:04.000Z", "text": "@rosedbarros T\u00e1 na hora do jair , t\u00e1 na hora do jair VOLTAR e pagar o Prato Feito que largou pra l\u00e1.VOLTA ITALIANO.", "id": "1622385599347834882"},{"created_at": "2023-02-05T22:45:52.000Z", "text": "@a_jessicao O Xand\u00e3o e a PF (que n\u00e3o \u00e9, Prato Feito) com certeza est\u00e3o", "id": "1622365922592784384"},{"created_at": "2023-02-05T21:29:25.000Z", "text": "pensando na galinhada do prato feito", "id": "1622346680992501767"},{"created_at": "2023-02-05T20:38:14.000Z", "text": "@cozinhapleigos Inclusive pelo que sei \u00e9 um prato feito com carnes super duras e cozido por horas.\n\nAqui tem gente que usa at\u00e9 carne nobre haha, o que parece perder um pouco o prop\u00f3sito de fazer \"carne de panela\".\n\nE pra mim n\u00e3o vai ketchup.", "id": "1622333801484455943"},{"created_at": "2023-02-05T19:42:04.000Z", "text": "DESCOBRI MELHOR PRATO FEITO DE FOZ FDS ESSA PORRA \u00c9 MUITO BOA CARALHO FILHO VAI SE FUDER", "id": "1622319667053318144"},{"created_at": "2023-02-05T18:41:52.000Z", "text": "@madrugatina Achei isso um prato feito pro povo circular fakenews", "id": "1622304515570470922"},{"created_at": "2023-02-05T17:25:32.000Z", "text": "@httagpp T\u00e1 todo mundo desesperado, o sistema de ingressos da eventim \u00e9 ruim e n\u00e3o acontece nada com os golpistas... prato feito", "id": "1622285308032176128"},{"created_at": "2023-02-05T17:19:19.000Z", "text": "J\u00e1 se passaram 6 meses e eu ainda n\u00e3o superei esse prato feito pelo meu amigo se achando o verdadeiro @chefdangalhardo por fazer frango cru \ud83e\udd23\ud83e\udd23\ud83e\udd23 https://t.co/eJUKoJI0gp", "id": "1622283743300915201"},{"created_at": "2023-02-05T17:18:19.000Z", "text": "Prato feito https://t.co/kQus5lv8G2", "id": "1622283491101614081"},{"created_at": "2023-02-05T16:24:00.000Z", "text": "@RacoonaChan Sou a favor de ser classificado como uma nova categoria. Sei l\u00e1 algo tipo PF(Prato Feito) da manh\u00e3 \ud83d\ude4f", "id": "1622269823395700742"},{"created_at": "2023-02-05T16:20:26.000Z", "text": "famoso prato feito \ud83e\udd23\ud83e\udd23", "id": "1622268926305370114"},{"created_at": "2023-02-05T15:50:43.000Z", "text": "@Rachel_psi_ mas o que \u00e9 isso PF \u00e9 prato feito \u00e9 porque a pol\u00edcia federal n\u00e3o existe mais no Brasil existe uma ruma de criminosos que faz a seguran\u00e7a de Alexandre de Moraes que na minha opini\u00e3o se eu vier no meu carro e tiver uma blitz eu passo por cima deles seja PRF ou PF", "id": "1622261447702061058"},{"created_at": "2023-02-05T15:48:52.000Z", "text": "@_xvilela Um prato feito ar condicionado e dormir at\u00e9 diz\u00ea chega \ud83d\ude4f\ud83d\ude44", "id": "1622260981102526469"},{"created_at": "2023-02-05T15:39:38.000Z", "text": "@gsepolava prato feito \u00e9 meu cu", "id": "1622258655901908992"},{"created_at": "2023-02-05T14:04:41.000Z", "text": "@cozinhabruta S\u00f3 de pensar que existe um prato feito com \"carac\u00f3is\", imediatamente associo a esses invasores rastejantes devoradores de plantas e portadores de vermes que podem MATAR humanos, chamados Achatina fulica...\nMuito nojento \ud83e\udd2e\nN\u00e3o comeria nem se chamasse \"escargot\".", "id": "1622234763611324417"},{"created_at": "2023-02-05T12:41:40.000Z", "text": "@RAQUELD20669859 \"O conceito \u00e9 diferente, voc\u00ea \u00e9 que se serve...\" Diferente pra quem e onde?\nEu me sirvo em casa, na minha m\u00e3e, na sogra, no Prato feito, no quilo... \n\nE em qualquer a\u00e7a\u00edteriazinha meia bunda de qualquer bairro...\n\n\"Conceito diferente...\" \n\nTaquemepariu...", "id": "1622213870222774273"},{"created_at": "2023-02-05T10:13:50.000Z", "text": "Bom dia. Comi um prato feito \u00e0s 6h da manh\u00e3. Isso \u00e9 almo\u00e7o ou janta? \ud83e\udd14 https://t.co/NaaIfAfNA8", "id": "1622176664590454786"},{"created_at": "2023-02-05T05:17:07.000Z", "text": "Sao paulo \u00e9 uma cidade tao Gourmet que o Prato Feito ta 50 REAIS sem suco sem nada kkkkkk https://t.co/z0NrCt7lZt", "id": "1622101997166919682"},{"created_at": "2023-02-05T05:00:15.000Z", "text": "@PLmidias Ser\u00e1 que a comida vem at\u00e9 a mesa com o prato feito ou eles que v\u00e3o l\u00e1 se servir igual churrasco de fam\u00edlia do Brasil? Kkkkkk", "id": "1622097751763722243"},{"created_at": "2023-02-05T02:58:33.000Z", "text": "@Camjobr prato feito", "id": "1622067123836145664"},{"created_at": "2023-02-05T00:32:07.000Z", "text": "o valor desse prato executivo jesus amado por acaso foi um prato feito pelo jacquin?", "id": "1622030272454598656"},{"created_at": "2023-02-04T23:17:19.000Z", "text": "@ouindireta o famoso prato feito", "id": "1622011448959410176"},{"created_at": "2023-02-04T21:45:47.000Z", "text": "Vim aqui no garota da Txr almo\u00e7ar\u2026 essa hr, acabou tudo! S\u00f3 prato feito \ud83d\ude12", "id": "1621988413086859264"},{"created_at": "2023-02-04T21:36:53.000Z", "text": "@wilkerleaods @randolfeap Corregedoria?\ud83e\udd14 PF?? Prato feito?\ud83e\udd14\ud83e\udd14", "id": "1621986171675877378"},{"created_at": "2023-02-04T20:42:14.000Z", "text": "quero comer prato feito", "id": "1621972418645426276"},{"created_at": "2023-02-04T19:44:43.000Z", "text": "Mais um excelente prato feito pelo gordinho de skin cozinheiro", "id": "1621957946497171457"},{"created_at": "2023-02-04T19:22:01.000Z", "text": "@furacaoodacpi @pedrubad @stylesnitter Ou de prato feito ou de puta feia?", "id": "1621952231749591041"},{"created_at": "2023-02-04T17:24:28.000Z", "text": "@satanatita um prato feito \ud83e\udd70", "id": "1621922651320057856"},{"created_at": "2023-02-04T17:13:26.000Z", "text": "DUDA PRATO FEITO, 15 REAIS", "id": "1621919875642933251"},{"created_at": "2023-02-04T16:08:42.000Z", "text": "Qual a necessidade de deixar se levar pela gula e comer um prato feito INTEIRO de feijoada??? Agora fica a\u00ed passando mal \n(Autocr\u00edtica", "id": "1621903583787581440"},{"created_at": "2023-02-04T15:50:17.000Z", "text": "@seilafihkkkk Prato feito", "id": "1621898950415360000"},{"created_at": "2023-02-04T15:13:16.000Z", "text": "ed acabei de macetar um prato feito de estrogonofe, acho q tinha umas 1milhao de calorias vou ir de base https://t.co/iPkFMsQbhj", "id": "1621889632039313409"},{"created_at": "2023-02-04T14:32:27.000Z", "text": "@hermionefear como assim marmita?\naquele prato feito ? ((legal", "id": "1621879363384868871"},{"created_at": "2023-02-04T13:12:20.000Z", "text": "@Metropoles O governo da desgra\u00e7a, corrup\u00e7\u00e3o e seus ministros incompetentes comunistas. Prato feito pro Brasil ir ladeira abaixo esses 4 anos.", "id": "1621859198404333568"},{"created_at": "2023-02-04T09:19:45.000Z", "text": "@TerraBrasilnot Alexandre de Morais quer saber se Bolsonaro repetiu a comida e pediu para a PF ( prato feito) que tome o depoimento em 24h antes do arroz esfriar", "id": "1621800668943056898"},{"created_at": "2023-02-04T07:59:44.000Z", "text": "Mandar fazer marmita pra fulano entregar \u00e9 t\u00e3o coisa de pobre j\u00e1 fiz muito inclusive, essa gente n tinha como mandar entregar comida de algum restaurante? Tinha que desviar at\u00e9 prato feito? Moedas em espelho d\u2019\u00e1gua, garrafas de vinho?? Eh eh pobreza de esp\u00edrito.", "id": "1621780531057754112"},{"created_at": "2023-02-04T06:45:55.000Z", "text": "essa a\u00ed n \u00e9 nem marmita q nem ces fala, \u00e9 prato feito memo, daqueles q c paga 40 real e vem ate azeite pra acompanhar", "id": "1621761954300805120"},{"created_at": "2023-02-04T06:10:06.000Z", "text": "A Bruna no ouvido do Gustavo e a Amanda no ouvido da Key. \nPrato feito para eles terem raz\u00e3o de falar amanh\u00e3.", "id": "1621752941534216192"},{"created_at": "2023-02-04T04:22:07.000Z", "text": "foi engra\u00e7ado quando eu mandei aquelas pizza l\u00e1 de prato feito, com feij\u00e3o arroz e batata frita falando q era normal aqui", "id": "1621725764130426881"},{"created_at": "2023-02-04T02:04:58.000Z", "text": "Fazendo quase 30 graus DE NOITE, maior calor e adivinha o que acontece bem na hora de eu botar meu prato de comida?\n\nFalta luz.\n\nAgora to no escuro, com o prato feito e morreno de calor.", "id": "1621691249735393281"},{"created_at": "2023-02-04T01:41:56.000Z", "text": "De fiel \u00e0 prato feito, \u00e9 foda", "id": "1621685455237308421"},{"created_at": "2023-02-04T01:40:33.000Z", "text": "pedi uma prato feito t\u00f4 muito feliz", "id": "1621685105616879617"},{"created_at": "2023-02-04T01:31:00.000Z", "text": "Ontem Ravi comeu seu primeiro prato feito, eu fico t\u00e3o orgulhosa do meu filho e ao mesmo tempo assustada de como o tempo voa \ud83d\ude2d\ud83e\udd0d", "id": "1621682701701971969"},{"created_at": "2023-02-04T01:27:42.000Z", "text": "@aroundortega ent\u00e3o eh prato feito msm", "id": "1621681872668336128"},{"created_at": "2023-02-04T01:27:25.000Z", "text": "@__sseuIgi prato feito amor", "id": "1621681802946510848"},{"created_at": "2023-02-04T01:05:33.000Z", "text": "@revistaoeste ??? Um prato feito para os humoristas e a policia. Abuso de autoridade, tamb\u00e9m, ao utilizar seus seguran\u00e7as para conter a v\u00edtima para n\u00e3o recuperar seu material de trabalho.", "id": "1621676297997918209"},{"created_at": "2023-02-03T22:31:38.000Z", "text": "ela foi entregar o pf (prato feito) dela aff https://t.co/Q2lQNPKSOC", "id": "1621637562312916997"},{"created_at": "2023-02-03T22:17:04.000Z", "text": "A plmd n tenho culpa q tu tem fama de rodada n linda se o povo acha isso problema seu kkkk, prato feito!", "id": "1621633897380417540"},{"created_at": "2023-02-03T22:01:18.000Z", "text": "O cara faz jantar pra Presidente nazista genocida de merda fdp at\u00e9 o \u00faltimo fio de cabelo mas pra cremosa n\u00e3o paga nem um prato feito.\n\u00c9 um fdp https://t.co/OPVjaVtWAA", "id": "1621629928427905024"},{"created_at": "2023-02-03T19:57:41.000Z", "text": "E o Lula, condenado em 4 Inst\u00e2ncias por unanimidade. Quando se \u00e9 , perseguido, politicamente, tem sempre um canalha instigando a corte contra ele. A\u00ed \u00e9 prato feito! E tem parlamentares que se prestam a essa jogo. Triste isso! https://t.co/RWn3XYu26S", "id": "1621598820369944577"},{"created_at": "2023-02-03T16:18:00.000Z", "text": "@atono_obliquo eu to fazendo um quadrinho da gar\u00e7onete do prato feito vem ai", "id": "1621543536876290052"},{"created_at": "2023-02-03T16:11:04.000Z", "text": "Eu tava eu l\u00e1 e Maca\u00e9 e pensei: t\u00f4 com vontade de comer comida \u00e1rabe. Fui ao Habib's e PLAU, n\u00e3o tinha um prato feito \u00e1rabe. Levantei, pedi licen\u00e7a e me retirei.\n\nStrogonoff eu como em casa, porra!", "id": "1621541790317674497"},{"created_at": "2023-02-03T15:47:24.000Z", "text": "Fui comer num restaurante gostosin, ai vem o prato feito\u2026 mandei a bocona num pur\u00ea e era de banana\u2026. queria morr\u00ea", "id": "1621535834041196544"},{"created_at": "2023-02-03T15:41:53.000Z", "text": "Mais@um dia comendo esses prato feito do centro \ud83d\ude1e\ud83d\ude1e", "id": "1621534447567835136"},{"created_at": "2023-02-03T15:15:22.000Z", "text": "detonei um prato feito agr \ud83d\ude0b", "id": "1621527774157742081"},{"created_at": "2023-02-03T14:45:25.000Z", "text": "A \u00fanica coisa que valeu a pena hj foi ter pago 10 reais num prato feito", "id": "1621520236595007490"},{"created_at": "2023-02-03T13:39:28.000Z", "text": "@wazasanches prato feito?\npolicia federal?\npound fair?", "id": "1621503640669388801"},{"created_at": "2023-02-03T12:58:28.000Z", "text": "@EduardoPerovano LEK, o como tu desconhece o prato feito mais popular do pa\u00eds \u00e9 algo muito insens\u00edvel pprt", "id": "1621493321993420800"},{"created_at": "2023-02-03T12:03:01.000Z", "text": "@ypiprds Prato feito?", "id": "1621479366466146304"},{"created_at": "2023-02-03T11:45:48.000Z", "text": "@babadofamososrj Pra quem gosta de bosta \u00e9 um prato feito", "id": "1621475033687138306"},{"created_at": "2023-02-03T11:23:09.000Z", "text": "Falta esses palha\u00e7os conversarem com a PF ( prato feito, por favor, primeiro fiscal)\nAhhh! POL\u00cdCIA FEDERAL MESMO , cadeia para voc\u00eas ser\u00e1 pr\u00eamio. Mas respeitaremos a justi\u00e7a da Constitui\u00e7\u00e3o que ser\u00e1 SEMPRE , direito de todos. At\u00e9 de voc\u00eas , lixos da humanidade. Have a Nice day \ud83e\udd19 https://t.co/AyIbDxSOZa", "id": "1621469332642332672"},{"created_at": "2023-02-03T11:10:52.000Z", "text": "A Lanchonete Alem\u00e3o serve marmita e prato feito para o almo\u00e7o https://t.co/BToU9FPITN via @guiasmi", "id": "1621466245395632128"},{"created_at": "2023-02-03T10:39:03.000Z", "text": "sempre que eu leio PF a \u00faltima coisa que me vem na cabe\u00e7a \u00e9 pol\u00edcia federal, a primeira \u00e9 prato feito https://t.co/ASpUdEcjZJ", "id": "1621458237982707713"},{"created_at": "2023-02-03T10:30:49.000Z", "text": "@jairmearrependi Prato Feito.", "id": "1621456164297867264"},{"created_at": "2023-02-03T05:57:53.000Z", "text": "\u201cquem divide multiplica\u201d fala mais prato feito, oq \u00e9 meu \u00e9 meu, oq \u00e9 seu, \u00e9 seu", "id": "1621387480552411136"},{"created_at": "2023-02-03T04:11:32.000Z", "text": "Me amarro nesse prato feito", "id": "1621360715402444801"},{"created_at": "2023-02-03T02:20:45.000Z", "text": "@slendergay_ prato feito?", "id": "1621332833506582529"},{"created_at": "2023-02-02T23:31:01.000Z", "text": "\u00fanica coisa boa que sulista fez \u00e9 chamar prato feito de a la minuta", "id": "1621290119545196546"},{"created_at": "2023-02-02T22:24:30.000Z", "text": "@camilacousseau tem tanto a vers\u00e3o alaminuta com feij\u00e3o e salada, quanto uma vers\u00e3o prato feito mas particularmente a alaminuta me ganhou", "id": "1621273381134794752"},{"created_at": "2023-02-02T22:05:57.000Z", "text": "@Sapo_pepe77 Muito espertos, Prato Feito, n\u00e3o vou cair nessa armadilha atroz", "id": "1621268711620362240"},{"created_at": "2023-02-02T21:46:40.000Z", "text": "@cacabylima Prato feito pra globolixo", "id": "1621263860287127558"},{"created_at": "2023-02-02T20:08:30.000Z", "text": "MANTENHA O PRATO FEITO DAS RUAS NO VIADUTO! - Assine a peti\u00e7\u00e3o! https://t.co/XUCNIhxsyT via @change_br", "id": "1621239156537008129"},{"created_at": "2023-02-02T19:19:04.000Z", "text": "Paella, anyone? (Prato feito pelo @xHelasdottir ) https://t.co/GnuBX1a4NE", "id": "1621226715312701440"},{"created_at": "2023-02-02T18:59:28.000Z", "text": "Fizeram o vape de vitamina logo vem a\u00ed o vape prato feito uma refei\u00e7\u00e3o completa em forma de fuma\u00e7a n\u00e3o vejo a hora \ud83d\ude4f\ud83c\udffb", "id": "1621221782349905923"},{"created_at": "2023-02-02T17:38:10.000Z", "text": "@nikolas_dm Aproveita e pede tambem sobre os tantos gastos do bonsonaro em suas mtociatas etc ..\u00e9 muito gasto com gasolina e PFS n\u00e9 - sei que prato feito \u00e9 caro, mas como estes do bonsonaro \u00e9 demais n\u00e9 ...bora", "id": "1621201323768090627"},{"created_at": "2023-02-02T17:01:21.000Z", "text": "quero um livro sobre massas. quero entender tudo sobre massa. quero ir pra It\u00e1lia. quero abrir um restaurante italiano em Macei\u00f3 e fazer os otarios pagarem 100 reais num prato feito por mim", "id": "1621192058974216192"},{"created_at": "2023-02-02T16:09:00.000Z", "text": "@rbcgaia PF = Prato feito\nNa real, Pol\u00edcia Federal", "id": "1621178883407237122"},{"created_at": "2023-02-02T15:43:46.000Z", "text": "45 reais um prato feito, meu Deus, sem suco.", "id": "1621172533658783744"},{"created_at": "2023-02-02T15:20:27.000Z", "text": "Ao vivo no #Balan\u00e7oGeral: m\u00e3e \u00e9 agredida por dona de restaurante ao tentar dividir prato feito com a filha. \n\n\u27a1\ufe0f Assista no @sigaplayplus: https://t.co/EsiKDUNakY https://t.co/2b1GaOD6ZM", "id": "1621166664426332160"},{"created_at": "2023-02-02T15:19:53.000Z", "text": "- Que vontade de comer um PF.\nEu- Um Por Fora???\n- N\u00e3o, prato feito..\nA vida de um arquivista/contador neh facil n", "id": "1621166521941913601"},{"created_at": "2023-02-02T14:56:23.000Z", "text": "@rcabrinicosta @a_postagem Marreco assado\ud83d\ude0b @SF_Moro no senado vai ser o nosso PF...prato feito \ud83d\ude02 ele \u00e9 fraco de TUDO \ud83d\ude09\ud83d\ude07", "id": "1621160609621622785"},{"created_at": "2023-02-02T13:46:23.000Z", "text": "Acho um absurdo o prato feito do conka ainda n\u00e3o ter m inscritos. \n\nGosto bastante do conte\u00fado desenvolvido, principalmente por ajudar a compartilhar as experi\u00eancias do futebol nos EUA. https://t.co/GuD2ctbC5P", "id": "1621142991800008706"},{"created_at": "2023-02-02T13:18:10.000Z", "text": "O que eu quero saber \u00e9 se a bosta do @MPF_PGR ou a @policiafederal V\u00c3O INVESTIGAR a farra que foi gastar dezenas de milhares de R$ em lanchonete de PF Prato-feito. N\u00e3o concorda, Exmo. @alexandre? https://t.co/M3eczWbhyJ", "id": "1621135893678669831"},{"created_at": "2023-02-02T13:09:52.000Z", "text": "Se gostam de  Futebol \ud83c\udfc8 ou \u26bd\ufe0f, basquete  \ud83c\udfc0 e comida Sigam esse canal!  Prato Feito do Conka https://t.co/ASjN5B3RZi", "id": "1621133803480846339"},{"created_at": "2023-02-02T13:04:26.000Z", "text": "12 seguidores para meu canal chegar aos primeiros 1000 inscritos. Me ajudem? Tem muita coisa l\u00e1 j\u00e1 preparando o clima para a Copa do Mundo de 2026. \n\nPRATO FEITO DO CONKA \u00e9 o nome l\u00e1 na rede de v\u00eddeos. Pq acho que se colocar o link aqui, o Twitter n\u00e3o vai distribuir.", "id": "1621132434376097793"},{"created_at": "2023-02-02T12:37:28.000Z", "text": "@euzinhaape Prato feito", "id": "1621125647224508416"},{"created_at": "2023-02-02T12:09:28.000Z", "text": "Um lugar cujo nome \u00e9 PRATO FEITO e n\u00e3o aceita vale refei\u00e7\u00e3o, sinceramente S\u00e3o Paulo...", "id": "1621118603973259264"},{"created_at": "2023-02-02T11:33:29.000Z", "text": "@HenriqueD13 PF = Prato Feito\nBarba = Barbacoa = Churrascaria", "id": "1621109545300013056"},{"created_at": "2023-02-02T11:03:49.000Z", "text": "@Estadao @EstadaoPolitica A\u00ed, Michele Bolsonaro, ser\u00e1 mesmo q n\u00e3o \u00e9 seu esposo quem deve estar com medo?\ud83d\ude2c\ud83d\ude05\nA\u00ed @alexandre e @MPF_PGR prato feito ouvir esse Senador melhor, hein?! Percam tempo n\u00e3o!", "id": "1621102082634964993"},{"created_at": "2023-02-02T03:29:44.000Z", "text": "@gabcultural prato feito", "id": "1620987807664586752"},{"created_at": "2023-02-02T03:16:13.000Z", "text": "prato feito eh uma maravilha https://t.co/rlzMFRvq83", "id": "1620984407942389763"},{"created_at": "2023-02-02T01:55:25.000Z", "text": "Restaurante com uma pegada diferente. Arroz e Feij\u00e3o do MST. Pre\u00e7o justo e comida boa. Prato Feito na Nestor Pestana. https://t.co/ZIcwIhUEK7", "id": "1620964072853495808"},{"created_at": "2023-02-02T00:50:16.000Z", "text": "@sindinfluencer Prato feito, marreco com omelete e quiabo.", "id": "1620947675117146112"},{"created_at": "2023-02-01T23:47:18.000Z", "text": "Prato feito, com arroz de mont\u00e3o, feij\u00e3o, salada a vontade e uns 3 peda\u00e7os de bife: 23 reais\n\nUm p\u00e3o de hamb\u00farguer com uma fatia de queijo e um bife: 25 reais\n\nN\u00e3o tem l\u00f3gica nenhuma esse pre\u00e7o absurdo.\nE olha que achei que viria um carne e queijo com respeito. Decepcionado", "id": "1620931831368683526"},{"created_at": "2023-02-01T22:10:30.000Z", "text": "esse podia ser tranquilamente um prato feito pelo meu pai https://t.co/kKxcaqLlz5", "id": "1620907468594479104"},{"created_at": "2023-02-01T21:28:16.000Z", "text": "V\u00e1rios que declaram o voto em Marinho mudaram. Por que ser\u00e1? Venderam-se? Com certeza. Por ser secreto, foi prato feito.", "id": "1620896843591819264"},{"created_at": "2023-02-01T21:18:11.000Z", "text": "@Estadao A diferen\u00e7a do governo nazi pra o atual \u00e9 simples, agora a PF(vulgo prato feito kkkk) tem autonomia pra trabalhar, ent\u00e3o vai aparecer muitos esc\u00e2ndalos, est\u00e1 s\u00f3 come\u00e7ando.", "id": "1620894305257758750"},{"created_at": "2023-02-01T20:00:41.000Z", "text": "@4382qwx @chefdangalhardo Deu at\u00e9 at\u00e9 de fome.\n\nEu em qualquer prato feito", "id": "1620874801203261440"},{"created_at": "2023-02-01T19:38:20.000Z", "text": "MANTENHA O PRATO FEITO DAS RUAS NO VIADUTO! - Assine a peti\u00e7\u00e3o! https://t.co/PRTpj7eit3 via @change_br Sua a\u00e7\u00e3o \u00e9 muito importante! E sua press\u00e3o continua sendo fundamental!Por\u00e9m, precisamos de garantia para continuar a atender as pessoas em situa\u00e7\u00e3o de rua e vulnerabilidade,", "id": "1620869174871625728"},{"created_at": "2023-02-01T18:53:20.000Z", "text": "MANTENHA O PRATO FEITO DAS RUAS NO VIADUTO! - Assine a peti\u00e7\u00e3o! https://t.co/U1IOXYZyXl via @change_br", "id": "1620857849537785858"},{"created_at": "2023-02-01T17:35:07.000Z", "text": "Almo\u00e7o de hoje quase finalizado. Iai, comeriam um prato feito por este Mister Xepa bonit\u00e3o? \ud83e\udee3\ud83d\ude0b\n\n#BBB23 | #TeamCris https://t.co/dnqBoEZE7H", "id": "1620838169087447040"},{"created_at": "2023-02-01T17:31:37.000Z", "text": "N\u00e3o tem comida caseira melhor do centro do que o prato feito ppd", "id": "1620837286979178498"},{"created_at": "2023-02-01T16:31:42.000Z", "text": "Prato Feito n\u00e3o quer saber de opini\u00e3o, sugiro sair das redes sociais, funcion\u00e1rios do Imperador https://t.co/OEwiLxy8jq", "id": "1620822209211293697"},{"created_at": "2023-02-01T14:58:16.000Z", "text": "Restaurante Don Chico...estamos abertos at\u00e9 as 15h..buffet livre...a KG...tbm Ala minutas...marmitas e Prato feito..estamos localizados em frente a Pol\u00edcia...lhe aguardamos !!! #garopaba Garopaba https://t.co/V4felYamqe", "id": "1620798696324743168"},{"created_at": "2023-02-01T14:47:31.000Z", "text": "Faz 6 dias hoje, 4 hot\u00e9is, vivendo de prato feito e marmitex ( n\u00e3o t\u00f4 reclamando) \u00e9 ainda n\u00e3o chegamos....mds socorrooo \ud83e\udd2f\ud83d\ude35\ud83d\ude2c\ud83d\ude2c", "id": "1620795988628885504"},{"created_at": "2023-02-01T12:50:44.000Z", "text": "@NoContextBrits Brazil says Hello!\nYou guys need to try the classic \"PF (Prato Feito)\". https://t.co/6nJOnb1NIv", "id": "1620766598465486848"},{"created_at": "2023-02-01T10:43:57.000Z", "text": "@venezianovital Reforma tribut\u00e1ria \u00e9 o caralho, \u00e9 aumento de impostos sim seu infeliz.  Em primeiro lugar voc\u00eas tem o dever de respeitar e fazer cumprir a constitui\u00e7\u00e3o.  Nunca ouvi falar dessa figura, mas deve ter sido eleito por famelicos, que ele consegue enganar facilmente com um prato feito.", "id": "1620734693368004608"},{"created_at": "2023-02-01T03:47:40.000Z", "text": "@phabelha @brunnosarttori Dono de garimpo n\u00e3o tem essa atitude, eles  tem na folha coron\u00e9is do EB, delgado do\"Prato Feito\" etc.\nIsso deve ser mais um, dentre tantos, sonegadores", "id": "1620629931825967108"},{"created_at": "2023-02-01T03:32:42.000Z", "text": "@laurotc um prato feito de milanesa com uma milanesa dentro", "id": "1620626166112747520"},{"created_at": "2023-02-01T01:44:17.000Z", "text": "Eu sei que essas comidas absurdas s\u00e3o baits mas eu fico nervosa pqp, porque diabos fazer comida com uma comida j\u00e1 pronta t\u00e1 lgd??? Um prato feito de hamb\u00farguer tomaaaar no cu https://t.co/qe5APhnWqM", "id": "1620598882983100417"},{"created_at": "2023-02-01T01:10:03.000Z", "text": "@lazarorosa25 E n\u00e3o t\u00f4 livrando os prato feito n\u00e3o\n\nN\u00e3o existe \u00e9tica nessas merda\n\n\u00c9tica pra eles \u00e9 coisa de boboca, coisa de trabalhador", "id": "1620590267400335360"},{"created_at": "2023-02-01T00:10:48.000Z", "text": "*se voc\u00ea n\u00e3o \u00e9 ou n\u00e3o mora em s\u00e3o paulo: \"pizza\" \u00e9 um prato feito de uma massa de p\u00e3o com hidrata\u00e7\u00e3o bem alta, assado em forno \u00e0 lenha e coberto de molho de tomate e outras coisas por cima (sendo queijo mu\u00e7arela uma cobertura muito comum mas n\u00e3o obrigat\u00f3ria) e carnes e vegetais", "id": "1620575358256033792"},{"created_at": "2023-01-31T23:48:35.000Z", "text": "@fersanvesso deve tirar uns 6 bruto mas o imposto, e acho que ganha vale ru, paga 83 centavos no prato feito", "id": "1620569767601127425"},{"created_at": "2023-01-31T22:34:58.000Z", "text": "@te__araujo @anna_martinsl @natilopesm Na minha cabe\u00e7a era um prato feito de carne de porco, n\u00e3o imaginava que era um p\u00e3o \ud83e\udd21", "id": "1620551238336282624"},{"created_at": "2023-01-31T21:58:32.000Z", "text": "@roderix1966 Na Rua XV de Novembro perto da antiga Bovespa (agora B3) vendia. Tinha um prato feito com v\u00e1rias op\u00e7\u00f5es em um restaurante na mesma rua chamado Eminente. Quem andava por ali nos anos 90 certamente ao menos viu o lugar. Era top a refei\u00e7\u00e3o.", "id": "1620542070569193473"},{"created_at": "2023-01-31T21:36:28.000Z", "text": "O problema maior \u00e9 voc\u00eas acharem que Strogonoff \u00e9 um prato feito e n\u00e3o um complemento de carne. Pra mim \u00e9 como se fosse um bife. Tem que ter arroz e feij\u00e3o sim https://t.co/yKCbiVzzFP", "id": "1620536518896140288"},{"created_at": "2023-01-31T21:19:21.000Z", "text": "@tchqlamets @marjoriestring q porra \u00e9 prato feito MDS", "id": "1620532208388960257"},{"created_at": "2023-01-31T21:16:59.000Z", "text": "@___kuIek @marjoriestring por favor ou prato feito ?", "id": "1620531615066918912"},{"created_at": "2023-01-31T19:30:24.000Z", "text": "Ritto M\u00e3e Terra Arroz Prato Feito 400G\nhttps://t.co/9AaPTtvomv", "id": "1620504792304058368"},{"created_at": "2023-01-31T19:22:27.000Z", "text": "Nossa do nada me deu uma vontade de comer aqueles prato feito, sabe, cm arroz, feij\u00e3o, bife, batata frita e um alface", "id": "1620502789196767232"},{"created_at": "2023-01-31T18:53:28.000Z", "text": "@_Carol4lves @douglas_barros pra c\u00e1 a gente chama picadinho o prato feito. O Par\u00e1 de bel\u00e9m \u00e9 muito diferente do nosso.", "id": "1620495499018264576"},{"created_at": "2023-01-31T18:25:45.000Z", "text": "@VeritasetfidePF @Leiro_ADPF @LulaOficial @fenadepol @FlavioDino Rip PF\nPF agora \u00e9 prato feito do molusco", "id": "1620488523144118273"},{"created_at": "2023-01-31T18:09:29.000Z", "text": "@tetaodokacchan prato feito", "id": "1620484429268525056"},{"created_at": "2023-01-31T17:13:48.000Z", "text": "Por isso sou contra aquela s\u00e9rie melosa porq \u00e9 prato feito pra pensamentos tipo \u201celes tinham que estar l\u00e1\u201d \u201cmorreu porq n\u00e3o deu ben\u00e7a pra m\u00e3e antes de sair\u201d \ud83e\udee0\ud83e\udee0\ud83e\udee0 https://t.co/DTBD3BULF1", "id": "1620470415180304385"},{"created_at": "2023-01-31T04:13:29.000Z", "text": "Vai prato feito, abre esse bueiro que voc\u00ea chama de boca", "id": "1620274040412987392"},{"created_at": "2023-01-31T01:54:46.000Z", "text": "Momento Prato de cozinha\n\nO que foi hoje?\n\nXacxuxa\n\nUm prato feito com um molho de tomate com piment\u00e3o e 4 ovos\n\nO prato leva esse nome por que voc\u00ea come com p\u00e3o e realmente xuca o p\u00e3o no molho\n\n\u00c9 um prato da Arg\u00e9lia https://t.co/sWEqeQ5fQo", "id": "1620239133452148737"},{"created_at": "2023-01-31T01:07:40.000Z", "text": "Uma tristeza minha, n\u00e3o conseguir ser uma enciclop\u00e9dia musical\nEu estudo e n\u00e3o lembro dos nomes das paradas \nEu hoje tentando lembrar o nome de uma m\u00fasica do Toninho Horta\n\n\"Ser\u00e1 que \u00e9 'janta', 'jantar'?\" \n\nNome da m\u00fasica 'Prato feito' \n\nDureza hahaha", "id": "1620227281125015552"},{"created_at": "2023-01-30T23:37:12.000Z", "text": "depois desse prato feito inteiramente com restinho de coisa da geladeira que eu fiz pro jantar eu merecia pelo menos uma vaguinha no masterchef", "id": "1620204511427178497"},{"created_at": "2023-01-30T21:00:27.000Z", "text": "@CinAlbuquerque @KaiserNewland @lybrjack FEIJOADA \u00e9 um prato feito a base de Feijao. nao existe apenas a feijoada brasileira, com feijao preto, em portugal existe varios tipos de feijoada, a base de feijao, com lula, com carne de porco, etc.", "id": "1620165066388832257"},{"created_at": "2023-01-30T21:00:01.000Z", "text": "O grupo Prato Feito das Ruas criou esse abaixo-assinado para pedir que continuem atuando debaixo do Viaduto Imperatriz Leopoldina, no Centro de Porto Alegre, no RS. \n\nQuer apoiar essa causa?\n \nAssine agora! Acesse: https://t.co/r0GQdZlft3", "id": "1620164956288163845"},{"created_at": "2023-01-30T20:59:34.000Z", "text": "concordo tbm que as por\u00e7oes estao aumentando, a reply no post do querido ta certa\n\ntipo hj quando eu vou em um restaurante e pe\u00e7o um prato feito aqui na europa, grandes chances de ser um prato gigantesco e desnecessario\n\nmas argumentar isso com fast food burgao NO BRASIL \u00e9 pica", "id": "1620164843994230784"},{"created_at": "2023-01-30T19:12:37.000Z", "text": "Vai monogamica corna, FALA AI DOS TEUS MEDO envolvendo relacionamento dos outros CHIFRUDA prato feito https://t.co/AK2ys3Mqh2", "id": "1620137928952545281"},{"created_at": "2023-01-30T16:59:54.000Z", "text": "Cheguei pegando minhas coisas pra fazer a atividade da facu, Dilsin veio com meu prato feito com direito a coquinha", "id": "1620104527923007488"},{"created_at": "2023-01-30T16:52:51.000Z", "text": "A\u00ed que vergonha de pedir Prato Feito. Eu dou duas garfadas e n aguento mais, a\u00ed smp sobra horrores de comida \ud83d\ude2d", "id": "1620102755619856384"},{"created_at": "2023-01-30T12:36:09.000Z", "text": "@silvianagata @caralhonath Silvia voc\u00ea n\u00e3o conhece a Barra da Tijuca aqui no rio onde o pessoal que trabalha nos pr\u00e9dios iu nas lojas de shopping n\u00e3o tem um restaurante barato pra comer arroz feij\u00e3o batata bife e salada \u00e9 s\u00f3 lanchonete e acabou. Um prato feito na Barra \u00e9 R$30 quem consegue comer?", "id": "1620038155339501568"},{"created_at": "2023-01-30T08:02:18.000Z", "text": "@GuardianDown3 @TorugoCampos @TheLastOfUsBR Deseperado nao,mas comer normal. E o cara j\u00e1 tinha tomado banho, ganhado roupas limpas, o prato feito servido na mesa, pq diabos viria um tiro naquele momento. At\u00e9 a postura do Bill j\u00e1 tava mais branda pra dizer o minimo. Pareceu \u00e9 q ele queria mais comer o Bill do q a comida.", "id": "1619969235740155907"},{"created_at": "2023-01-30T04:45:35.000Z", "text": "@Casamatabeija Odeio echii, mas ne aqui vai.\nCaso: Erza ela \u00e9 foda, mas q pena q virou fanservise. \nBeijo: a Esdeath s\u00f3 pq ela morre com o tatsume.\nMato: Saeko odeio echii e isso \u00e9 prato feito pra essa merda", "id": "1619919733184417792"},{"created_at": "2023-01-30T03:50:54.000Z", "text": "MANTENHA O PRATO FEITO DAS RUAS NO VIADUTO! - Assine a peti\u00e7\u00e3o! https://t.co/MFo7SOiclm via @change_br", "id": "1619905969592610816"},{"created_at": "2023-01-30T02:40:36.000Z", "text": "@miaujeann @homoidiotas a\u00ed seria prato feito pros nazis derrubarem tamb\u00e9m", "id": "1619888280870465536"},{"created_at": "2023-01-29T21:42:13.000Z", "text": "tamb\u00e9m conheci um mini querido enquanto almo\u00e7ava e dividi o peixe do prato feito c ele https://t.co/IfNp0QnpuJ", "id": "1619813188056535040"},{"created_at": "2023-01-29T21:41:46.000Z", "text": "hoje foi um dia t\u00e3o gostosinho.... acordei tarde, dei comida pro cachorro, pra gata e pras galinhas, sa\u00ed de bicicleta at\u00e9 achar um lugar aberto pra comer e almocei um prato feito responsa, fui tomar um sorvete de sobremesa, voltei pra casa e dormi mais ainda... paz", "id": "1619813074604789761"},{"created_at": "2023-01-29T20:52:01.000Z", "text": "@luttyshimanutri gente, as calorias s\u00e3o assustadoras p um \u00fanico lanche sim e digo mais: n\u00e3o \u00e9 s\u00f3 sobre calorias, mas tb sobre a qualidade das calorias. t\u00f4 vendo gente aqui comparando um fast food com prato feito (pf)... sugiro buscar sobre o guia alimentar p popula\u00e7\u00e3o br (2014), s\u00f3 jogar no +", "id": "1619800553705570307"},{"created_at": "2023-01-29T20:14:10.000Z", "text": "Meu ex me levava o prato feito na cama\ud83d\ude0c\ud83d\ude0f", "id": "1619791030110535680"},{"created_at": "2023-01-29T20:10:31.000Z", "text": "@denisoupenha @SandrieleParan1 @Aguiarthur Arthur Aguiar, meu prato feito de cada dia \ud83e\udd29\ud83d\udd25", "id": "1619790111331479553"},{"created_at": "2023-01-29T19:43:19.000Z", "text": "fala fala fala d mim mas at\u00e9 teve q inventar oq dizer,vai la otaria,sua fama \u00e9 d rodada e a minha de metida,mil vezes metida dq prato feito \ud83e\udd23", "id": "1619783266336374785"},{"created_at": "2023-01-29T17:23:28.000Z", "text": "@juamadl sabe oq do\u00ed mais que isso? mina linda q \u00e9 prato feito", "id": "1619748074087403520"},{"created_at": "2023-01-29T17:03:47.000Z", "text": "@fferreira_xp Acho que vale a experi\u00eancia! E tamb\u00e9m vai muito de cada um, as hist\u00f3rias de guerra s\u00e3o bem legais, mas quando tr\u00e1s para o meio corporativo, \u00e9 o mesmo \u201cprato-feito\u201d que demais livros abordam, assim como os treinamentos dentro das companhias, muita mesmice, estou meio saturado \ud83d\ude02", "id": "1619743118445903872"},{"created_at": "2023-01-29T16:49:36.000Z", "text": "vai la mata morre por macho, bora prato feito\nfala que voc\u00ea se ama sem gaguejar\ud83e\udd23", "id": "1619739550443769856"},{"created_at": "2023-01-29T13:58:45.000Z", "text": "H\u00e1 6 anos o projeto social Prato Feito das Ruas distribui caf\u00e9 da manh\u00e3 e 1200 marmitas para cerca de 700 pessoas em situa\u00e7\u00e3o de rua. Tem tamb\u00e9m os Barbeiros na Rua, que realiza cortes de cabelo, pedicure e manicure, os M\u00e9dicos do Mundo.\ud83e\uddf6\nhttps://t.co/qVGDyPu6lE https://t.co/KH7oXIPp3q", "id": "1619696553433899008"},{"created_at": "2023-01-29T12:25:23.000Z", "text": "@wladiane_c @menezeslks @luttyshimanutri Parece que voc\u00ea n\u00e3o sabe que tem at\u00e9 PF (prato feito) com 1200 calorias...\n\nhttps://t.co/jPmp66QHCF", "id": "1619673058717085696"},{"created_at": "2023-01-29T07:50:50.000Z", "text": "@leiatheinvestor Depois da interfer\u00eancia na ''Prato Feito'' a porteira ficou escancarada.", "id": "1619603963271344129"},{"created_at": "2023-01-29T05:13:56.000Z", "text": "@ferreirajpcrvg @livbrandao O cara \u00e9 branco, bonito por\u00e9m babaca. Prato feito para ser pego para Cristo.", "id": "1619564477657255936"},{"created_at": "2023-01-29T03:15:24.000Z", "text": "prato feito do Pantanal KKKKKKKKKKKKKKKKKKKKKKKK", "id": "1619534648203444231"},{"created_at": "2023-01-29T01:04:48.000Z", "text": "Enqto nossos jogadores estiverem dando entrevistas, dizendo o que rola nos treinos, nesse oba-oba imenso, estaremos \u00e0 merc\u00ea disso, qdo o resultado for ruim, prato feito para os antis. \nCad\u00ea a assessoria deste time?!", "id": "1619501782744592384"},{"created_at": "2023-01-29T00:11:59.000Z", "text": "sil\u00eancio que a marmitinha vai falar que eu tenho inveja dela, vai prato feito fala\ud83e\udd70", "id": "1619488490168647683"},{"created_at": "2023-01-28T22:35:36.000Z", "text": "prato feito https://t.co/9iRZjS9mai", "id": "1619464236014665731"},{"created_at": "2023-01-28T22:19:32.000Z", "text": "Prefeito, moradoras(es) de Rua sem o Prato Feito? https://t.co/qkJnfIzZ5J", "id": "1619460191275356162"},{"created_at": "2023-01-28T18:34:09.000Z", "text": "@JornalOGlobo Vem Bozo...O cambur\u00e3o da Prato Feito te espera. https://t.co/d8z6wetBOU", "id": "1619403471123525632"},{"created_at": "2023-01-28T17:32:12.000Z", "text": "@laiscvrz Awwwwn \u2764\ufe0f\n\nAmiga, \u00e9 no Prato Feito. Do ladinho do arte e pizza", "id": "1619387882019622913"},{"created_at": "2023-01-28T16:36:11.000Z", "text": "@AVicencotto Guarda 30,00 pra pagar um prato feito pra mim aqui no cantinho caseiro quando vir \ud83e\udd1d\ud83c\udffc", "id": "1619373784129212419"},{"created_at": "2023-01-28T16:06:04.000Z", "text": "@roderix1966 Uma que trabalhou para mim contou que em certa casa que trabalhou fora servido um prato feito \u00e0 base de camar\u00e3o. Depois do almo\u00e7o, a patroa proibiu expressamente de comer o camar\u00e3o que sobrou, mas permitiu que misturasse apenas o caldo com arroz para comer. Gente p\u00e9ssima.", "id": "1619366206053679104"},{"created_at": "2023-01-28T14:55:38.000Z", "text": "@Stalinspears \ud83e\udd23\ud83e\udd23\ud83e\udd23\ud83e\udd23\ud83e\udd23\ud83e\udd23\ud83e\udd23\nPra quem gosta \u00e9 um prato feito.", "id": "1619348479230488577"},{"created_at": "2023-01-28T14:54:54.000Z", "text": "\ud83e\uddc4\ud83c\udf36\ufe0f TEMPEROS DA LIA!\n\ud83e\udd33 Chame AGORA no ZAP:\nhttps://t.co/uE10HZh7uo\n\ud83d\udcf2\ud83d\udcac 037991264427\n\ud83c\udf7d\ufe0f Coma \u00e0 vontade por 35 REAIS\n\ud83c\udf7d\ufe0f Prato Feito apenas 25 REAIS\n\ud83c\udf7d\ufe0f No Quilo s\u00f3 41,90\n\ud83c\udf7d\ufe0f O MELHOR MARMITEX: \n16 REAIS Grande / 13 REAIS M\u00e9dio\n\ud83d\udce6 Entrega s\u00f3 5 REAIS\n\ud83d\udccc Benjamin Guimar\u00e3es, 740 https://t.co/nX1ousD2X8", "id": "1619348294815330304"},{"created_at": "2023-01-28T14:10:27.000Z", "text": "@nonoinvestidor Com tanta gente por a\u00ed matando cachorro a grito, se procurar bem direitinho, consegue encontrar um \"bem bom\" em troca de um prato feito.", "id": "1619337111425155073"},{"created_at": "2023-01-28T13:01:30.000Z", "text": "@DoutorTio E tamb\u00e9m diferencia PF de prato feito e prato feito de refei\u00e7\u00e3o.", "id": "1619319758146670592"},{"created_at": "2023-01-28T05:59:40.000Z", "text": "Prato feito pra edi\u00e7\u00e3o ele chorando, conseguiu bones #BBB23", "id": "1619213599028936704"},{"created_at": "2023-01-28T03:27:23.000Z", "text": "@criadocurry Pf=prato feito", "id": "1619175276101124096"},{"created_at": "2023-01-28T02:56:19.000Z", "text": "silencio, a marmitinha de 13 anos que morre por macho, vai falar que pega cara que namora, vai prato feito, fala", "id": "1619167459294203905"},{"created_at": "2023-01-28T02:43:15.000Z", "text": "@siteptbr Os dois saiam pra comer.\n\nOs caras pra comer ela\nE ela pra comer Prato Feito", "id": "1619164170116816897"},{"created_at": "2023-01-28T01:37:32.000Z", "text": "sil\u00eancio, a marmitinha de 13 anos que morre por macho, vai falar que pega cara que namora. vai prato feito, fala", "id": "1619147632882110464"},{"created_at": "2023-01-28T00:41:06.000Z", "text": "MANTENHA O PRATO FEITO DAS RUAS NO VIADUTO! - Assine a peti\u00e7\u00e3o! https://t.co/5lnalOVLZU via @change_br", "id": "1619133429593042947"},{"created_at": "2023-01-28T00:33:43.000Z", "text": "@nandabics a ignorada na prato feito de jacund\u00e1 diz coisas tamb\u00e9m", "id": "1619131572699140097"},{"created_at": "2023-01-28T00:11:07.000Z", "text": "Prato feito", "id": "1619125883889160192"},{"created_at": "2023-01-27T23:26:21.000Z", "text": "n\u00e3o posso xingar o prato feito de jacund\u00e1 que saco https://t.co/mGXwAuKYTr", "id": "1619114617841799171"},{"created_at": "2023-01-27T22:39:43.000Z", "text": "@oiIuiz A PF, na verdade, estava procurando um prato feito, se enganou e prendeu uma confeiteira de bolo!", "id": "1619102884729061376"},{"created_at": "2023-01-27T21:22:16.000Z", "text": "@oiIuiz PF, Prato Feito da xandrina.", "id": "1619083393823805440"},{"created_at": "2023-01-27T18:58:28.000Z", "text": "Eu n entendo quem posta tudo em tempo real, foto do lugar q vc t\u00e1, localiza\u00e7\u00e3o, trajeto???? Video mostrando escola e nome da escola, uniforme tipo?? Cad\u00ea a no\u00e7\u00e3o? \u00c9 literalmente um prato feito pra sequestrador", "id": "1619047204257423360"},{"created_at": "2023-01-27T17:52:54.000Z", "text": "PF (Prato Feito) e n\u00f3s pensando que em breve seriamos uma Venezuela. Agora meu chapa! J\u00e1 estamos a caminho de nos tornaremos uma Cor\u00e9ia do Norte. https://t.co/3D34cqOMNp", "id": "1619030701936107520"},{"created_at": "2023-01-27T17:39:55.000Z", "text": "Nos \u00faltimos dias a Prato Feito das Ruas lutou contra o receio de ser removida do Viaduto do Brooklyn, no Centro de PoA, onde serve mais de mil marmitas por semana para popula\u00e7\u00e3o vulner\u00e1vel da cidade.\n\nEm reuni\u00e3o com a prefeitura ficou decidido o seguinte:\n\nhttps://t.co/8ZgVOHhW8k", "id": "1619027437404426246"},{"created_at": "2023-01-27T17:25:50.000Z", "text": "@oiIuiz Essa \u00e9 a PF\u2026. Uma prato feito\u2026..", "id": "1619023893624401920"},{"created_at": "2023-01-27T17:20:39.000Z", "text": "@nosrednav17 @Urublog 10 x R$35? Qto custa um prato feito na tua \u00e1rea? D\u00e1 um PF por m\u00eas. S\u00f3 comer um a menos.", "id": "1619022587354550272"},{"created_at": "2023-01-27T17:18:26.000Z", "text": "Ainda prefiro o Roched\u00e3o (prato feito) de Tropeiro e ovo poche do BOL\u00c3O. Que nostalgia! https://t.co/onMpYvxtlt", "id": "1619022027922489344"},{"created_at": "2023-01-27T16:45:14.000Z", "text": "Pega eles l\u00e1 prato feito", "id": "1619013675301609473"},{"created_at": "2023-01-27T16:27:01.000Z", "text": "amassei um prato feito e um de penne ao molho de bolonhesa \ud83d\ude45\ud83c\udffb\u200d\u2640\ufe0f", "id": "1619009088465301504"},{"created_at": "2023-01-27T16:08:11.000Z", "text": "pedi um prato feito o negocio veio comida pra 3 pessoas f\u00e1cil, comi 1/3 sofrendo cara, suando j\u00e1", "id": "1619004349602226178"},{"created_at": "2023-01-27T15:57:41.000Z", "text": "\"pq n d\u00e1 de ficar indo comer prato feito\" vcs subestimam minha capacidade de comer pouco", "id": "1619001709908611077"}]